Workbook

Sheet Cover
B11: Template
B13: TRAINING TOPIC SYLLABUS
F17: Document Code
F18: Version | I18: 1.0
F19: Effective Date

Sheet JavaSpring_Syllabus
A1: Java Spring-Syllabus
A2: The course goal to focus developers with the skills and mindset required to become senior Java backend engineers, focusing on Spring Boot, AWS, and scalable system design, high-performance applications and solving real-world production issues.
A3: Developer will develop the ability to design, optimize, and troubleshoot modern distributed systems effectively.
A5: 1 | B5: Topic Name | C5: JAVA for Dev2-3
A6: 2 | B6: Topic Code | C6: FT_Java
A7: 3 | B7: Version | C7: v3
A8: 4 | B8: Target Training Audience Job Profile | C8: Software Engineer
A9: 5 | B9: Target Training Audience Job Rank | C9: Dev2 — Fast Track rank-up lên Dev3
A10: 6 | B10: Target Training Audience Description | C10: Developers with 1-3 years of experience working with Java Backend, etc. (~ DEV level 2.5)
A11: 7 | B11: Course Objectives | C11: This topic is to introduce high level Java Framework concepts to engineering employees who have Mid-level Backend Developer and help them upskill through lessons, examples, and practical exercises specifically designed for real-world project environments at Fsoft. The topic cover following output standards
C13: Name of Skills (Select from the link) | D13: Level of Skill Outcomes (Select a filter) | E13: Skill Priority | F13: Job Outputs
C14: Object-Oriented Programming (OOP) | D14: Level 3: Advanced | E14: Primary | F14: Current: - Writes functional Java code with basic OOP and applies common design patterns (Strategy, Factory). - Uses basic concurrency features (thread pool, CompletableFuture) but limited in debugging concurrency issues. Future: - Designs clean, extensible, and maintainable code with solid architecture principles (SOLID, clean boundaries). - Understands and resolves concurrency problems (race condition, deadlock) and optimizes async processing.
C15: Spring Framework | D15: Level 3: Advanced | E15: Primary | F15: Current: - Builds REST APIs with standard structure (Controller, Service, Repository). - Implements validation, pagination, and basic exception handling. Future: - Designs production-ready APIs with clear contracts, idempotency, and error handling strategy. - Applies clean architecture (layered/hexagonal) and optimizes application structure for scalability and maintainability.
C16: System Design | D16: Level 2: Intermediate | E16: Secondary | F16: Current: - Understands basic service separation and can build simple microservices. - Has limited experience with distributed system challenges. Future: - Designs scalable microservices architecture with proper boundaries and communication patterns. - Applies distributed system concepts (event-driven, eventual consistency, retry, idempotency, fault tolerance).
C19: LO - Codes | D19: Learning Outcomes (LO) | E19: Bloom Level | F19: Current–Future Balance (70% of learning time focuses on current needs, and 30% on future needs)
C20: LO1 | D20: Explain the roles of the JVM, JRE, and JDK; use Java data types, operators, arrays, control flow, switch expressions, and varargs to describe the implementation and testing of a StringCalculator for defined addition and subtraction inputs. | E20: B2 – Understand | F20: Current Needs
C21: LO2 | D21: Implement and unit-test an employee payroll model using encapsulated classes and records, inheritance, abstraction, overriding, overloading and polymorphism. | E21: B3 – Apply | F21: Current Needs
C22: LO3 | D22: Select an interface or abstract class for a stated design; use generics and Java collections safely; implement a generic collection with a defined exception hierarchy and tests for core operations and error cases. | E22: B4 – Analyze | F22: Current Needs
C23: LO4 | D23: Build a Java data-processing pipeline that reads CSV data with NIO, filters, groups, aggregates and sorts records with Streams, produces JSON output, and analyzes sequential and parallel execution under stated benchmark conditions. | E23: B4 – Analyze | F23: Current Needs
C24: LO5 | D24: Configure Spring beans, scopes, lifecycle, profiles and type-safe properties; use constructor injection and explicit bean selection to implement and test multiple notification-service implementations. | E24: B3 – Apply | F24: Current Needs
C25: LO6 | D25: Build and test a Spring MVC CRUD API with correct request mapping, HTTP responses, content negotiation, request validation, service-level state-transition checks and standardized ProblemDetail error responses. | E25: B3 – Apply | F25: Current Needs
C26: LO7 | D26: Model and test an e-commerce data layer with JPA entities and relationships; justify cascade and fetch choices; implement transactional repository queries, Flyway migrations and persistence tests. | E26: B4 – Analyze | F26: Current Needs
... C31: LO12 | D31: Analyze the completed solution against functional, security, performance, reliability, and maintainability criteria; examine evidence from source code, tests, logs, and metrics to identify strengths, weaknesses, and improvement opportunities. | E31: B4 – Analyze | F31: Future Needs
A34: 8 | B34: Topic Outline | C34: Name of Skills (Same skill list in row 13) | D34: Unit | E34: Name of Skills (Same skill list in row 13) | F34: Unit
C35: Object-Oriented Programming (OOP) | D35: Unit 1: Java Platform & Language Basics Unit 2: OOP in Java Unit 3: Interface, Generics, Collections & Exception Unit 4: Stream API, Concurrency & File I/O
C36: Spring Framework | D36: Unit 5: Spring Boot Core & IoC Container Unit 6: Spring MVC – In-Depth REST API Unit 7: Spring Data JPA & Database Unit 8: Spring Security & JPA Performance Unit 9: Caching, Async, File Handling & External API Unit 10: Testing, Documentation, Monitoring & Docker
C37: System Design | D37: Unit 11: Project Planning & Implementation Unit 12: Implementation Sprint & Final Defense
A42: 9 | B42: Time Allocation | C42: Concept/Lecture | D42: =JavaSpring_Schedule!H66 -> 0 | E42: <Concepts, theory> | F42: <5400 minutes>
C43: Self-learning | D43: =JavaSpring_Schedule!H67 -> 0.44444444 | E43: <Self-learning>
C44: Seminar/Workshop | D44: =JavaSpring_Schedule!H68 -> 0 | E44: <Seminar/Workshop>
C45: Class Meeting | D45: =JavaSpring_Schedule!H69 -> 0.027777778 | E45: <Class Meeting>
C46: Assignment/Lab | D46: =JavaSpring_Schedule!H70 -> 0.44444444 | E46: <Assignment, Lab>
C47: Guides/Review | D47: =JavaSpring_Schedule!H71 -> 0.055555556 | E47: <Quiz, assignment review Assignment guides>
C48: Test/Quiz | D48: =JavaSpring_Schedule!H72 -> 0 | E48: <Daily quiz>
C49: Exam | D49: =JavaSpring_Schedule!H73 -> 0.027777778 | E49: <Pre-Test, Final Topic Test>
A50: 10 | B50: Training Materials & Environments | C50: Text book | D50: <n/a>
D51: <n/a>
C52: References | D52: <n/a>
D53: <n/a>
D54: <n/a>
C55: Technical requirements | D55: <n/a>
A56: 11 | B56: Assessment Scheme | C56: Assignments | D56: 100% completed all assigned assignments of the course
C57: Final Test - Theory | D57: Pass final theory test (rate > 80%)
C58: Final Test - Practice | D58: Pass practice test (rate > 80%)
C59: Passing criteria | D59: Total topic GPA >= 8/10 Attendant >=80% of training time
A60: 12 | B60: Training Delivery Principles | C60: Trainees | D60: - DEV2 Software Engineer with at least 2 years of development experience, including at least 1 year of hands-on Java backend experience. - Can implement basic Java applications using OOP, collections, exception handling and unit tests. - Has basic knowledge of relational databases, REST APIs, Git and backend workflows.
C61: Trainer | D61: - Trainer and mentor has a good knowledge of the Java, Spring Framework, AWS or other cloud SDK platform that has been evaluated by GST
C62: Training | D62: Mentor supports Q&A, exercise review and technical guidance. - Learners submit assignments with source code and test evidence for review. - Module checks are used to verify progress. - Final assessment includes theory, practical implementation and solution defense. - OJT tasks require defined acceptance criteria, evidence and mentor sign-off.
C63: Re-Test | D63: 1 | E63: Only allow each trainee to retake the test up to 1 times; Re-exam the same structure as the Final Test
C64: Marking | D64: - Trainer marks the Final Exam Practice - If the trainees have to retake test, the score will be calculated: + The score >=8, the score will be 8 + The scroe <8, the score will be that score
C65: Waiver Criteria | D65: Trainees pass the quick test Trainer Audit: rank B
C66: Others | D66: Trainers can allow trainee to complete homework and submit the next day

Sheet JavaSpring_Schedule
A1: =JavaSpring_Syllabus!C5 & " - Training Schedule" -> JAVA for Dev2-3 - Training Schedule
A2: Training Unit/Chapter | C2: Day | D2: Content Outlines | E2: Learning Objectives | F2: Delivery Type | G2: Duration (mins) | H2: Trainer | I2: Training Format | J2: Date | K2: Training Materials / Logistics & General Notes (Required, For Reference, etc.)
A3: Unit 1 | B3: Java Platform & Language Basics | C3: Day 1 | D3: JVM, JRE, JDK & Data Types + JVM Architecture + JRE vs JDK + Primitive Types & Wrappers + String & String Pool + Arrays & varargs | E3: LO1 | F3: Self-learning | G3: 120 | I3: Online | J3: 46252 | K3: Required: • JVM Architecture: https://docs.oracle.com/javase/specs/jvms/se17/html/jvms-2.html • JVM vs JRE vs JDK: https://www.baeldung.com/jvm-vs-jre-vs-jdk • Data Types: https://docs.oracle.com/javase/tutorial/java/data/index.html • String & String Pool: https://www.baeldung.com/java-string-pool • String Immutability: https://www.baeldung.com/java-string-immutability • Autoboxing: https://docs.oracle.com/javase/tutorial/java/data/autoboxing.html
D4: Assignment | E4: LO1 | F4: Assignment/Lab | G4: 30 | I4: Online | J4: 46252 | K4: Required: • JVM Architecture: https://docs.oracle.com/javase/specs/jvms/se17/html/jvms-2.html • JVM vs JRE vs JDK: https://www.baeldung.com/jvm-vs-jre-vs-jdk • Data Types: https://docs.oracle.com/javase/tutorial/java/data/index.html • String & String Pool: https://www.baeldung.com/java-string-pool • Autoboxing: https://docs.oracle.com/javase/tutorial/java/data/autoboxing.html
C5: Day 2 | D5: Operators & Control Flow + Operators + Switch expressions + Pattern Matching + Loops & Stream intro | E5: LO1 | F5: Self-learning | G5: 120 | I5: Online | J5: 46253 | K5: Required: • Operators: https://docs.oracle.com/javase/tutorial/java/nutsandbolts/operators.html • Control Flow: https://docs.oracle.com/javase/tutorial/java/nutsandbolts/flow.html • Switch Expressions: https://docs.oracle.com/javase/tutorial/java/nutsandbolts/switch.html • Pattern Matching (JLS): https://docs.oracle.com/javase/specs/jls/se17/html/jls-14.html#jls-14.30 • For/While Loops: https://docs.oracle.com/javase/tutorial/java/nutsandbolts/for.html
D6: Guides/Review | E6: LO1 | F6: Guides/Review | G6: 30 | H6: PhonNT1/LinhNT102 | I6: Virtual | J6: 46255
C7: Day 3 | D7: - Lab 1: Implement `StringCalculator` applying String immutability and primitive optimization - Input: a string containing a simple arithmetic expression (addition/subtraction) - Output: integer result | E7: LO1 | F7: Assignment/Lab | G7: 150 | I7: Online | J7: 46254 | K7: Required: • String & String Pool: https://www.baeldung.com/java-string-pool • String Immutability: https://www.baeldung.com/java-string-immutability • Operators: https://docs.oracle.com/javase/tutorial/java/nutsandbolts/operators.html • Control Flow: https://docs.oracle.com/javase/tutorial/java/nutsandbolts/flow.html
A8: Unit 2 | B8: OOP in Java | C8: Day 4 | D8: Classes, Objects, Encapsulation + Class structure + Access modifiers + Encapsulation + Records + this & super | E8: LO2 | F8: Self-learning | G8: 120 | I8: Online | J8: 46255 | K8: Required: • OOP Concepts: https://docs.oracle.com/javase/tutorial/java/javaOO/index.html • Constructors: https://www.baeldung.com/java-constructors • Access Modifiers: https://www.baeldung.com/java-access-modifiers • Encapsulation: https://www.baeldung.com/java-encapsulation • Records: https://www.baeldung.com/java-records
D9: Assignment | E9: LO2 | F9: Assignment/Lab | G9: 30 | I9: Online | J9: 46255 | K9: Required: • OOP Concepts: https://docs.oracle.com/javase/tutorial/java/javaOO/index.html • Constructors: https://www.baeldung.com/java-constructors • Access Modifiers: https://www.baeldung.com/java-access-modifiers • Encapsulation: https://www.baeldung.com/java-encapsulation • Records: https://www.baeldung.com/java-records
C10: Day 5 | D10: Inheritance, Polymorphism & Abstract + Inheritance + Method Overriding + Method Overloading + Polymorphism + Abstract class | E10: LO2 | F10: Self-learning | G10: 120 | I10: Online | J10: 46258 | K10: Required: • Inheritance: https://www.baeldung.com/java-inheritance • Polymorphism: https://www.baeldung.com/java-polymorphism • Abstract Class: https://www.baeldung.com/java-abstract-class • Override/Overloading: https://www.baeldung.com/java-method-overloading-riding
D11: Guides/Review | E11: LO2 | F11: Guides/Review | G11: 30 | H11: PhonNT1/LinhNT102 | I11: Virtual | J11: 46262
C12: Day 6 | D12: - Assignment 2: Employee Management System - Base `Employee` abstract (id, name, baseSalary) + method `calculateSalary()` abstract - Subclass: `Developer` (overtimeHours, bonusRate), `Manager` (teamSize, kpiMultiplier) - `PayrollService` calculates total salary using polymorphism - Uses a Record for `EmployeeDTO` - Unit tests verify the correctness of each salary type | E12: LO2 | F12: Assignment/Lab | G12: 150 | I12: Online | J12: 46259 | K12: Required: • OOP Concepts: https://docs.oracle.com/javase/tutorial/java/javaOO/index.html • Inheritance: https://www.baeldung.com/java-inheritance • Polymorphism: https://www.baeldung.com/java-polymorphism • Abstract Class: https://www.baeldung.com/java-abstract-class
A13: Unit 3 | B13: Interface, Generics, Collections & Exception | C13: Day 7 | D13: Interface, Inner Classes & Enums + Interface + Abstract vs Interface + Inner Classes + Enums + SOLID Principles | E13: LO3 | F13: Self-learning | G13: 120 | I13: Online | J13: 46260 | K13: Required: • Interface & Inheritance: https://docs.oracle.com/javase/tutorial/java/IandI/index.html • Java Interface: https://www.baeldung.com/java-interface • Inner Classes & Enums: https://www.baeldung.com/java-inner-class-enums • Enum: https://www.baeldung.com/java-enum • SOLID Principles: https://www.baeldung.com/java-solid-principles
D14: Assignment | E14: LO3 | F14: Assignment/Lab | G14: 30 | I14: Online | J14: 46260 | K14: Required: • Interface & Inheritance: https://docs.oracle.com/javase/tutorial/java/IandI/index.html • Java Interface: https://www.baeldung.com/java-interface • Inner Classes & Enums: https://www.baeldung.com/java-inner-class-enums • SOLID Principles: https://www.baeldung.com/java-solid-principles
C15: Day 8 | D15: Generics, Collections & Exception Handling + Generics + List implementations + Set/Map + Exception hierarchy + try-with-resources | E15: LO3 | F15: Self-learning | G15: 120 | I15: Online | J15: 46261 | K15: Required: • Generics: https://docs.oracle.com/javase/tutorial/java/generics/index.html • Java Generics: https://www.baeldung.com/java-generics • Collections: https://docs.oracle.com/javase/tutorial/collections/index.html • Java Collections: https://www.baeldung.com/java-collections • Exceptions: https://docs.oracle.com/javase/tutorial/essential/exceptions/index.html • Java Exceptions: https://www.baeldung.com/java-exceptions • Try-with-resources: https://www.baeldung.com/java-try-with-resources
D16: Guides/Review | E16: LO3 | F16: Guides/Review | G16: 30 | H16: PhonNT1/LinhNT102 | I16: Virtual | J16: 46262
C17: Day 9 | D17: - Lab 3: Custom Collection & Exception Framework - Implement `SimpleArrayList<E>` with dynamic array (add, get, remove, size, iterator) - Implement `SimpleHashMap<K,V>` with separate chaining - Custom exception hierarchy: `DataAccessException` → `DuplicatedKeyException`, `KeyNotFoundException` - Test coverage ≥ 80% | E17: LO3 | F17: Assignment/Lab | G17: 150 | I17: Online | J17: 46262 | K17: Required: • Generics: https://docs.oracle.com/javase/tutorial/java/generics/index.html • Collections: https://docs.oracle.com/javase/tutorial/collections/index.html • Java Collections: https://www.baeldung.com/java-collections • Exceptions: https://www.baeldung.com/java-exceptions • Try-with-resources: https://www.baeldung.com/java-try-with-resources
A18: Unit 4 | B18: Stream API, Concurrency & File I/O | C18: Day 10 | D18: Lambda & Stream API Chuyên Sâu + Lambda & Functional Interface + Stream pipeline + Collectors + Optional deep dive + Parallel Stream | E18: LO4 | F18: Self-learning | G18: 120 | I18: Online | J18: 46268 | K18: Required: • Lambda & Functional Interface: https://www.baeldung.com/java-functional-interface • Stream Filter & Lambda: https://www.baeldung.com/java-stream-filter-lambda • Stream API: https://www.baeldung.com/java-stream • Java Streams: https://www.baeldung.com/java-streams • Collectors: https://www.baeldung.com/java-stream-collectors
D19: Assignment | E19: LO4 | F19: Assignment/Lab | G19: 30 | I19: Online | J19: 46268 | K19: Required: • Lambda & Functional Interface: https://www.baeldung.com/java-functional-interface • Stream API: https://www.baeldung.com/java-stream • Java Streams: https://www.baeldung.com/java-streams • Collectors: https://www.baeldung.com/java-stream-collectors
C20: Day 11 | D20: Concurrency & File I/O + Thread fundamentals + synchronized & volatile + ExecutorService + NIO & File I/O + Serialization | E20: LO4 | F20: Self-learning | G20: 120 | I20: Online | J20: 46269 | K20: Required: • Thread Fundamentals: https://www.baeldung.com/java-thread-lifecycle • Synchronized: https://www.baeldung.com/java-synchronized • Volatile: https://www.baeldung.com/java-volatile • Synchronization (Oracle): https://docs.oracle.com/javase/tutorial/essential/concurrency/sync.html • ExecutorService: https://docs.oracle.com/javase/tutorial/essential/concurrency/executors.html • File I/O: https://docs.oracle.com/javase/tutorial/essential/io/fileio.html • Java I/O: https://www.baeldung.com/java-io • NIO.2 File API: https://www.baeldung.com/java-nio-2-file-api • Serialization: https://www.baeldung.com/java-serialization
D21: Guides/Review | E21: LO4 | F21: Guides/Review | G21: 30 | H21: PhonNT1/LinhNT102 | I21: Virtual | J21: 46276
C22: Day 12 | D22: - Assignment 4: Data Processing Pipeline - Read file CSV 500K rows (simulated sales data) - Stream transform: filter invalid → group by category → aggregate revenue → sort top 10 - Parallel vs sequential benchmark (JMH) - Thread-safe result accumulator - Export report ra JSON | E22: LO4 | F22: Assignment/Lab | G22: 150 | I22: Online | J22: 46272 | K22: Required: • Stream API: https://www.baeldung.com/java-stream • Collectors: https://www.baeldung.com/java-stream-collectors • File I/O: https://docs.oracle.com/javase/tutorial/essential/io/fileio.html • Java I/O: https://www.baeldung.com/java-io • NIO.2 File API: https://www.baeldung.com/java-nio-2-file-api
A23: Unit 5 | B23: Spring Boot Core & IoC Container | C23: Day 13 | D23: Spring Boot Fundamentals & Bean Lifecycle + Spring Boot Architecture + IoC Container + Bean scopes + Bean lifecycle + Stereotype annotations | E23: LO5 | F23: Self-learning | G23: 120 | I23: Online | J23: 46273 | K23: Required: • IoC Container: https://docs.spring.io/spring-framework/reference/core/beans/introduction.html • Bean Scopes: https://docs.spring.io/spring-framework/reference/core/beans/factory-scopes.html • Spring Boot Overview: https://www.baeldung.com/spring-boot
D24: Assignment | E24: LO5 | F24: Assignment/Lab | G24: 30 | I24: Online | J24: 46273 | K24: Required: • IoC Container: https://docs.spring.io/spring-framework/reference/core/beans/introduction.html • Bean Scopes: https://docs.spring.io/spring-framework/reference/core/beans/factory-scopes.html • Spring Boot Overview: https://www.baeldung.com/spring-boot
C25: Day 14 | D25: Dependency Injection & Configuration + DI Types + @Autowired resolution + @Configuration & @Bean + @ConfigurationProperties + Profiles | E25: LO5 | F25: Self-learning | G25: 120 | I25: Online | J25: 46274 | K25: Required: • Bean Scopes: https://docs.spring.io/spring-framework/reference/core/beans/factory-scopes.html • IoC & DI: https://www.baeldung.com/inversion-control-and-dependency-injection-in-spring • Auto-configuration: https://docs.spring.io/spring-boot/reference/using/auto-configuration.html
D26: Guides/Review | E26: LO5 | F26: Guides/Review | G26: 30 | H26: PhonNT1/LinhNT102 | I26: Virtual | J26: 46276
C27: Day 15 | D27: - Assignment 5: Multi-module Notification Service - Interface `NotificationService` → EmailSender, SmsSender, PushSender - @Qualifier or @Profile select implementation - @ConfigurationProperties for each config (SMTP, Twilio, Firebase) - Retry logic when send fail - The Factory pattern creates the correct sender based on the notification type. | E27: LO5 | F27: Assignment/Lab | G27: 150 | I27: Online | J27: 46275 | K27: Required: • @ConfigurationProperties: https://www.baeldung.com/configuration-properties-in-spring-boot • External Config: https://docs.spring.io/spring-boot/reference/features/external-config.html • IoC Container: https://docs.spring.io/spring-framework/reference/core/beans/introduction.html
A28: Unit 6 | B28: Spring MVC — In-Depth REST API | C28: Day 16 | D28: Controller & Request/Response + @RestController + Request mapping + Parameter handling + ResponseEntity + Content negotiation | E28: LO6 | F28: Self-learning | G28: 120 | I28: Online | J28: 46276 | K28: Required: • Request Mapping: https://docs.spring.io/spring-framework/reference/web/webmvc/mvc-controller/ann-requestmapping.html • Spring RequestMapping: https://www.baeldung.com/spring-requestmapping • ResponseEntity: https://www.baeldung.com/spring-response-entity
D29: Assignment | E29: LO6 | F29: Assignment/Lab | G29: 30 | I29: Online | J29: 46276 | K29: Required: • Request Mapping: https://docs.spring.io/spring-framework/reference/web/webmvc/mvc-controller/ann-requestmapping.html • Spring RequestMapping: https://www.baeldung.com/spring-requestmapping • ResponseEntity: https://www.baeldung.com/spring-response-entity
C30: Day 17 | D30: Validation & Exception Handling + Bean Validation + Custom Validator + @RestControllerAdvice + ProblemDetail (RFC 9457) + Business Exception hierarchy | E30: LO6 | F30: Self-learning | G30: 120 | I30: Online | J30: 46279 | K30: Required: • Bean Validation: https://www.baeldung.com/spring-boot-bean-validation • Custom Validator: https://www.baeldung.com/spring-mvc-custom-validator • ProblemDetail (RFC 9457): https://www.baeldung.com/spring-boot-return-errors-problemdetail
D31: Guides/Review | E31: LO6 | F31: Guides/Review | G31: 30 | H31: PhonNT1/LinhNT102 | I31: Virtual | J31: 46283
C32: Day 18 | D32: - Lab 6: User & Task Management API - CRUD Task: title, description, status (TODO/IN_PROGRESS/DONE), priority, dueDate - Validation: title notBlank, dueDate in future, valid status transition - Custom validator: @ValidStatusTransition - Global exception handler ProblemDetail - Postman collection export | E32: LO6 | F32: Assignment/Lab | G32: 150 | I32: Online | J32: 46280 | K32: Required: • Request Mapping: https://docs.spring.io/spring-framework/reference/web/webmvc/mvc-controller/ann-requestmapping.html • Custom Validator: https://www.baeldung.com/spring-mvc-custom-validator • ProblemDetail: https://www.baeldung.com/spring-boot-return-errors-problemdetail
A33: Unit 7 | B33: Spring Data JPA & Database | C33: Day 19 | D33: Entity Design & Relationships + Entity mapping + Relationships + @ManyToMany + Cascade & Orphan Removal + FetchType | E33: LO7 | F33: Self-learning | G33: 120 | I33: Online | J33: 46281 | K33: Required: • JPA Entities: https://www.baeldung.com/jpa-entities • JPA Associations: https://www.baeldung.com/jpa-hibernate-associations • JPA Cascade Types: https://www.baeldung.com/jpa-cascade-types • Lazy/Eager Loading: https://www.baeldung.com/hibernate-lazy-eager-loading
D34: Assignment | E34: LO7 | F34: Assignment/Lab | G34: 30 | I34: Online | J34: 46281 | K34: Required: • JPA Entities: https://www.baeldung.com/jpa-entities • JPA Associations: https://www.baeldung.com/jpa-hibernate-associations • Lazy/Eager Loading: https://www.baeldung.com/hibernate-lazy-eager-loading
C35: Day 20 | D35: Query, Transaction & Patterns + Repository + Pagination & Sort + Projection + @Transactional + Auditing | E35: LO7 | F35: Self-learning | G35: 120 | I35: Online | J35: 46282 | K35: Required: • JPA Cascade Types: https://www.baeldung.com/jpa-cascade-types • Lazy/Eager Loading: https://www.baeldung.com/hibernate-lazy-eager-loading • JPA Pagination & Sorting: https://www.baeldung.com/spring-data-jpa-pagination-sorting • Database Auditing: https://www.baeldung.com/database-auditing-jpa
D36: Guides/Review | E36: LO7 | F36: Guides/Review | G36: 30 | H36: PhonNT1/LinhNT102 | I36: Virtual | J36: 46283
C37: Day 21 | D37: - Assignment 7: E-Commerce Data Layer - Entities: User, Product, Category, Order, OrderItem - Full relationships + cascade correct - Repository query: top-selling products, orders by date range, user history - Flyway migration (V1__init.sql → V2__seed_data.sql) - @DataJpaTest integration test | E37: LO7 | F37: Assignment/Lab | G37: 150 | I37: Online | J37: 46283 | K37: Required: • JPA Pagination & Sorting: https://www.baeldung.com/spring-data-jpa-pagination-sorting • Database Auditing: https://www.baeldung.com/database-auditing-jpa • Spring Data Repositories: https://docs.spring.io/spring-data/jpa/reference/repositories.html
A38: Unit 8 | B38: Spring Security & JPA Performance | C38: Day 22 | D38: Authentication with Spring Security + JWT + Security Architecture + JWT Structure + JWT Flow + Stateless Session + Password Encoding | E38: LO8 | F38: Self-learning | G38: 120 | I38: Online | J38: 46286 | K38: Required: • JWT with Spring Security: https://docs.spring.io/spring-security/reference/servlet/oauth2/resource-server/jwt.html • Password Storage: https://docs.spring.io/spring-security/reference/features/authentication/password-storage.html • Stateless Session: https://docs.spring.io/spring-security/reference/servlet/authentication/session-management.html
D39: Assignment | E39: LO8 | F39: Assignment/Lab | G39: 30 | I39: Online | J39: 46286 | K39: Required: • JWT with Spring Security: https://docs.spring.io/spring-security/reference/servlet/oauth2/resource-server/jwt.html • Password Storage: https://docs.spring.io/spring-security/reference/features/authentication/password-storage.html • Stateless Session: https://docs.spring.io/spring-security/reference/servlet/authentication/session-management.html
C40: Day 23 | D40: Authorization & JPA Performance + Method Security + CORS & CSRF + N+1 Problem + Batch fetching + Soft Delete | E40: LO8 | F40: Self-learning | G40: 120 | I40: Online | J40: 46287 | K40: Required: • Method Security: https://www.baeldung.com/spring-security-method-security • CSRF Protection: https://www.baeldung.com/spring-security-csrf • CSRF (Official): https://docs.spring.io/spring-security/reference/servlet/exploits/csrf.html • N+1 Problem: https://vladmihalcea.com/n-plus-1-query-problem/
D41: Guides/Review | E41: LO8 | F41: Guides/Review | G41: 30 | H41: PhonNT1/LinhNT102 | I41: Virtual | J41: 46290
C42: Day 24 | D42: - Lab 8: Auth Service + Performance Optimization - Register + Login + Refresh + Logout (Redis blacklist) - @PreAuthorize role-based: CUSTOMER vs ADMIN - Product list API: fix N+1 when load category - Benchmark before/after optimize - Security integration test with @WithMockUser | E42: LO8 | F42: Assignment/Lab | G42: 150 | I42: Online | J42: 46288 | K42: Required: • JWT with Spring Security: https://docs.spring.io/spring-security/reference/servlet/oauth2/resource-server/jwt.html • N+1 Problem: https://vladmihalcea.com/n-plus-1-query-problem/ • Hibernate Soft Delete: https://vladmihalcea.com/hibernate-softdelete-annotation/ • Batch Insert/Update: https://vladmihalcea.com/how-to-batch-insert-and-update-statements-with-hibernate/
A43: Unit 9 | B43: Caching, Async, File Handling & External API | C43: Day 25 | D43: Caching & Async Processing + Spring Cache + Redis Cache + Cache Patterns + @Async + @Scheduled | E43: LO9 | F43: Self-learning | G43: 120 | I43: Online | J43: 46289 | K43: Required: • Spring Cache: https://www.baeldung.com/spring-cache-tutorial • Getting Started with Caching: https://spring.io/guides/gs/caching • Redis Cache (Spring Data): https://docs.spring.io/spring-data/redis/reference/redis/redis-cache.html
D44: Assignment | E44: LO9 | F44: Assignment/Lab | G44: 30 | I44: Online | J44: 46289 | K44: Required: • Spring Cache: https://www.baeldung.com/spring-cache-tutorial • Redis Cache: https://www.baeldung.com/spring-boot-redis-cache • Getting Started with Caching: https://spring.io/guides/gs/caching
C45: Day 26 | D45: File Upload/Download & External API + Multipart Upload + Download + WebClient + Resilience + CSV/Excel Export | E45: LO9 | F45: Self-learning | G45: 120 | I45: Online | J45: 46290 | K45: Required: • File Upload: https://www.baeldung.com/spring-file-upload • Uploading Files Guide: https://spring.io/guides/gs/uploading-files • WebClient: https://www.baeldung.com/spring-5-webclient • Circuit Breaker: https://www.baeldung.com/spring-boot-circuit-breaker-vs-retry • Java CSV: https://www.baeldung.com/java-csv
D46: Guides/Review | E46: LO9 | F46: Guides/Review | G46: 30 | H46: PhonNT1/LinhNT102 | I46: Virtual | J46: 46290
C47: Day 27 | D47: - Assignment 9: Product & Order Features - Cache product list, category tree. Evict on create/update/delete. - @Async: order confirmation email, inventory update - @Scheduled: cancel pending orders > 30 min - Product image upload + thumbnail - WebClient call payment gateway (mock) with circuit breaker - Export orders CSV (admin) | E47: LO9 | F47: Assignment/Lab | G47: 150 | I47: Online | J47: 46293 | K47: Required: • Spring Cache: https://www.baeldung.com/spring-cache-tutorial • Redis Cache: https://www.baeldung.com/spring-boot-redis-cache • @Async: https://www.baeldung.com/spring-async • @Scheduled: https://www.baeldung.com/spring-scheduled-tasks • File Upload: https://www.baeldung.com/spring-file-upload • WebClient: https://www.baeldung.com/spring-5-webclient • Resilience4j: https://www.baeldung.com/spring-boot-resilience4j
A48: Unit 10 | B48: Testing, Documentation, Monitoring & Docker | C48: Day 28 | D48: Testing Spring Boot + Unit Testing + @WebMvcTest + @DataJpaTest + Integration Test + Testcontainers | E48: LO10 | F48: Self-learning | G48: 120 | I48: Online | J48: 46294 | K48: Required: • Spring Boot Testing: https://www.baeldung.com/spring-boot-testing • Testing Spring Boot Applications: https://docs.spring.io/spring-boot/reference/testing/spring-boot-applications.html • JUnit 5: https://www.baeldung.com/junit-5 • Integration Testing: https://www.baeldung.com/integration-testing-in-spring
D49: Assignment | E49: LO10 | F49: Assignment/Lab | G49: 30 | I49: Online | J49: 46294 | K49: Required: • Spring Boot Testing: https://www.baeldung.com/spring-boot-testing • Testing Spring Boot Applications: https://docs.spring.io/spring-boot/reference/testing/spring-boot-applications.html • JUnit 5: https://www.baeldung.com/junit-5
C50: Day 29 | D50: Documentation, Logging, Monitoring & Docker + OpenAPI / Swagger + Structured Logging + Actuator & Metrics + Docker + docker-compose | E50: LO10 | F50: Self-learning | G50: 120 | I50: Online | J50: 46295 | K50: Required: • OpenAPI / SpringDoc: http://springdoc.org/ • Structured Logging: https://www.baeldung.com/spring-boot-structured-logging • Actuator: https://www.baeldung.com/spring-boot-actuators • Testcontainers: https://testcontainers.com/guides/testing-spring-boot-rest-api-using-testcontainers/ • Testcontainers for Spring Boot: https://docs.spring.io/spring-boot/reference/testing/testcontainers.html
D51: Guides/Review | E51: LO10 | F51: Guides/Review | G51: 30 | H51: PhonNT1/LinhNT102 | I51: Virtual | J51: 46297
C52: Day 30 | D52: - Lab 10: Production Readiness - Unit test + Integration test (Testcontainers) for all service - JaCoCo coverage report ≥ 75% - OpenAPI doc for all endpoint - JSON structured logging + traceId propagation - Actuator + Prometheus metrics + custom HealthIndicator - Dockerfile + docker-compose.yml (app + DB + Redis) - GitHub Actions CI: build → test → docker build | E52: LO10 | F52: Assignment/Lab | G52: 150 | I52: Online | J52: 46296 | K52: Required: • Spring Boot Testing: https://www.baeldung.com/spring-boot-testing • Testcontainers: https://testcontainers.com/guides/testing-spring-boot-rest-api-using-testcontainers/ • OpenAPI / SpringDoc: http://springdoc.org/ • Docker with Spring Boot: https://www.baeldung.com/spring-boot-docker-images • Docker Compose: https://www.baeldung.com/docker-compose-support-spring-boot
A53: Unit 11 | B53: Project Planning & Implementation | C53: Day 31 | D53: System Design & Project Kickoff + Architecture overview + API design | E53: LO11 | F53: Class Meeting | G53: 150 | I53: Online | J53: 46297 | K53: Required: • Spring Boot Reference: https://docs.spring.io/spring-boot/index.html • Structuring Your Code: https://docs.spring.io/spring-boot/reference/using/structuring-your-code.html • Spring MVC: https://docs.spring.io/spring-framework/reference/web/webmvc.html • Building REST API: https://www.baeldung.com/building-a-restful-web-service-with-spring
C54: Day 32 | D54: System Design & Project Kickoff + Database design + Error handling strategy + Development workflow | E54: LO11 | F54: Assignment/Lab | G54: 150 | I54: Online | J54: 46300 | K54: Required: • Spring Data Repositories: https://docs.spring.io/spring-data/jpa/reference/repositories.html • JPA Entity: https://docs.spring.io/spring-data/jpa/reference/jpa/entity-persistence.html • Exception Handling: https://www.baeldung.com/exception-handling-for-rest-with-spring • ProblemDetail: https://www.baeldung.com/spring-problem-detail
C55: Day 33 | D55: Development Sprint 1 - Implement core entities + repositories + migrations - Auth module (register, login, JWT) - User profile API - Category CRUD - Daily standup + progress review | E55: LO6, LO7, LO8, LO11 | F55: Assignment/Lab | G55: 150 | I55: Online | J55: 46301 | K55: Required: • JPA Entity: https://docs.spring.io/spring-data/jpa/reference/jpa/entity-persistence.html • JPA Cascade Types: https://www.baeldung.com/jpa-cascade-types • JWT with Spring Security: https://docs.spring.io/spring-security/reference/servlet/oauth2/resource-server/jwt.html • Spring Data Repositories: https://docs.spring.io/spring-data/jpa/reference/repositories.html • Pagination & Sort: https://www.baeldung.com/spring-data-jpa-sort
A56: Unit 12 | B56: Implementation Sprint & Final Defense | C56: Day 34 | D56: Development Sprint 2 - Product CRUD + search + filter + pagination - Product image upload - Cart management - Caching setup (categories, products) | E56: LO6, LO7, LO9, LO12 | F56: Assignment/Lab | G56: 150 | I56: Online | J56: 46302 | K56: Required: • Spring Data Repositories: https://docs.spring.io/spring-data/jpa/reference/repositories.html • Pagination & Sort: https://www.baeldung.com/spring-data-jpa-sort • File Upload: https://www.baeldung.com/spring-file-upload • Spring Cache: https://www.baeldung.com/spring-cache-tutorial
C57: Day 35 | D57: Development Sprint 3 - Order checkout flow - Order management (user + admin) - @Async email notification - Export CSV (admin) - Docker + docker-compose finalize - CI pipeline verify | E57: LO8, LO9, LO10, LO12 | F57: Assignment/Lab | G57: 150 | I57: Online | J57: 46303 | K57: Required: • @Transactional: https://www.baeldung.com/spring-transactional-propagation-isolation • @Async: https://www.baeldung.com/spring-async • Docker with Spring Boot: https://www.baeldung.com/spring-boot-docker-images • Docker Compose: https://www.baeldung.com/docker-compose-support-spring-boot • Java CSV: https://www.baeldung.com/java-csv
C58: Day 36 | D58: Final Defense | E58: LO10, LO11, LO12 | F58: Exam | G58: 150 | I58: Online | J58: 46304 | K58: Required: • Spring Boot Testing: https://www.baeldung.com/spring-boot-testing • Testcontainers: https://docs.spring.io/spring-boot/reference/testing/testcontainers.html • Docker with Spring Boot: https://www.baeldung.com/spring-boot-docker-images • OpenAPI / SpringDoc: http://springdoc.org/
A59: Unit 13 | B59: Final test | C59: Day 37 | D59: Final theory | E59: LO1, LO2, LO3, LO4, LO5, LO6, LO7, LO8, LO9, LO10 | F59: Exam | G59: 60 | I59: Offline | J59: 46307 | K59: Required: • Java Language Specification (JLS): https://docs.oracle.com/javase/specs/jls/se17/html/index.html • Spring Boot Reference: https://docs.spring.io/spring-boot/index.html • Spring Framework Reference: https://docs.spring.io/spring-framework/reference/index.html • Baeldung Java Tutorials: https://www.baeldung.com/java-tutorial • Baeldung Spring Tutorials: https://www.baeldung.com/spring-tutorial
C60: Day 38 | D60: Final practice | E60: LO5, LO6, LO7, LO8, LO9, LO10, LO11, LO12 | F60: Exam | G60: 300 | I60: Offline | J60: 46308
A61: Unit 14 | B61: OJT Phase | C61: Day 39- Day 64 | D61: Learners work with project tasks in FSU Project | E61: LO6, LO7, LO8, LO9, LO10, LO11, LO12 | F61: Assignment/Lab | G61: 1980 | I61: Offline
D62: Mentor support during OJT Phase | E62: LO10, LO11, LO12 | F62: Guides/Review | G62: 1980 | I62: Offline
A63: Unit 15 | B63: Evaluation Phase | C63: Day 65 - Day 66 | D63: Evaluate learners after training and OJT phase | E63: LO10, LO11, LO12 | F63: Exam | G63: 600 | I63: Virtual
F66: Concept/Lecture | G66: =SUMIF(F$4:F$58,F66,G$4:G$58) -> 0 | H66: =G66/$G$74 -> 0
F67: Self-learning | G67: =SUMIF(F$3:F$58,F67,G$3:G$58) -> 2400 | H67: =G67/$G$74 -> 0.44444444
F68: Seminar/Workshop | G68: =SUMIF(F$3:F$58,F68,G$3:G$58) -> 0 | H68: =G68/$G$74 -> 0
F69: Class Meeting | G69: =SUMIF(F$3:F$58,F69,G$3:G$58) -> 150 | H69: =G69/$G$74 -> 0.027777778
F70: Assignment/Lab | G70: =SUMIF(F$3:F$58,F70,G$3:G$58) -> 2400 | H70: =G70/$G$74 -> 0.44444444
F71: Guides/Review | G71: =SUMIF(F$3:F$58,F71,G$3:G$58) -> 300 | H71: =G71/$G$74 -> 0.055555556
F72: Test/Quiz | G72: =SUMIF(F$3:F$58,F72,G$3:G$58) -> 0 | H72: =G72/$G$74 -> 0
F73: Exam | G73: =SUMIF(F$3:F$58,F73,G$3:G$58) -> 150 | H73: =G73/$G$74 -> 0.027777778
F74: Total Time | G74: =SUM(G66:G73) -> 5400 | H74: =SUM(H66:H73) -> 1
F75: Current–Future Balance
F76: Current Needs | G76: =SUM(G3:G47) -> 4050 | H76: =G76/$G$78 -> 0.75
F77: Future Needs | G77: =SUM(G48:G58) -> 1350 | H77: =G77/$G$78 -> 0.25
F78: Total Time | G78: =SUM(G76:G77) -> 5400 | H78: =SUM(H76:H77) -> 1

Sheet Author and Rec of Changes
A1: AUTHORSHIP
B2: Role | C2: Name | D2: Account | E2: Unit | F2: Notes
B3: Creator | C3: Nguyễn Tấn Phôn | D3: PhonNT1 | E3: GST.CEN | F3: First version
B4: Reviewer
B5: Approver
A6: RECORD OF CHANGES
A7: *A - Added M - Modified D - Deleted
B9: Date | C9: Changes | E9: A* M, D | F9: Contents | G9: Version
B10: 46234 | C10: Create new | E10: A | F10: Syllabus of Java Spring | G10: 3

Sheet DV-IDENTITY-0
A1: =IF(JavaSpring_Syllabus!1:1,"AAAAAH7b/wA=",0) -> #VALUE! | B1: =AND(JavaSpring_Syllabus!#REF!,"AAAAAH7b/wE=") -> #ERROR! | C1: =AND(JavaSpring_Syllabus!B1,"AAAAAH7b/wI=") -> #VALUE! | D1: =AND(JavaSpring_Syllabus!C1,"AAAAAH7b/wM=") -> #VALUE! | E1: =AND(JavaSpring_Syllabus!D1,"AAAAAH7b/wQ=") -> #VALUE! | F1: =AND(JavaSpring_Syllabus!E1,"AAAAAH7b/wU=") -> #VALUE! | G1: =AND(JavaSpring_Syllabus!#REF!,"AAAAAH7b/wY=") -> #ERROR! | H1: =AND(JavaSpring_Syllabus!#REF!,"AAAAAH7b/wc=") -> #ERROR! | I1: =IF(JavaSpring_Syllabus!2:2,"AAAAAH7b/wg=",0) -> 0 | J1: =AND(JavaSpring_Syllabus!A2,"AAAAAH7b/wk=") -> #VALUE! | K1: =AND(JavaSpring_Syllabus!B2,"AAAAAH7b/wo=") -> #VALUE! | L1: =AND(JavaSpring_Syllabus!C2,"AAAAAH7b/ws=") -> #VALUE! | M1: =AND(JavaSpring_Syllabus!D2,"AAAAAH7b/ww=") -> #VALUE! | N1: =AND(JavaSpring_Syllabus!E2,"AAAAAH7b/w0=") -> #VALUE! | O1: =AND(JavaSpring_Syllabus!#REF!,"AAAAAH7b/w4=") -> #ERROR! | P1: =AND(JavaSpring_Syllabus!#REF!,"AAAAAH7b/w8=") -> #ERROR! | Q1: =IF(JavaSpring_Syllabus!5:5,"AAAAAH7b/xA=",0) -> 0 | R1: =AND(JavaSpring_Syllabus!A5,"AAAAAH7b/xE=") -> #VALUE! | S1: =AND(JavaSpring_Syllabus!B5,"AAAAAH7b/xI=") -> #VALUE! | T1: =AND(JavaSpring_Syllabus!C5,"AAAAAH7b/xM=") -> #VALUE! | U1: =AND(JavaSpring_Syllabus!D5,"AAAAAH7b/xQ=") -> #VALUE! | V1: =AND(JavaSpring_Syllabus!E5,"AAAAAH7b/xU=") -> #VALUE! | W1: =AND(JavaSpring_Syllabus!#REF!,"AAAAAH7b/xY=") -> #ERROR! | X1: =AND(JavaSpring_Syllabus!#REF!,"AAAAAH7b/xc=") -> #ERROR! | Y1: =IF(JavaSpring_Syllabus!6:6,"AAAAAH7b/xg=",0) -> 0 | Z1: =AND(JavaSpring_Syllabus!A6,"AAAAAH7b/xk=") -> #VALUE! | AA1: =AND(JavaSpring_Syllabus!B6,"AAAAAH7b/xo=") -> #VALUE! | AB1: =AND(JavaSpring_Syllabus!C6,"AAAAAH7b/xs=") -> #VALUE! | AC1: =AND(JavaSpring_Syllabus!D6,"AAAAAH7b/xw=") -> #VALUE! | AD1: =AND(JavaSpring_Syllabus!E6,"AAAAAH7b/x0=") -> #VALUE! | AE1: =AND(JavaSpring_Syllabus!#REF!,"AAAAAH7b/x4=") -> #ERROR! | AF1: =AND(JavaSpring_Syllabus!#REF!,"AAAAAH7b/x8=") -> #ERROR! | AG1: =IF(JavaSpring_Syllabus!7:7,"AAAAAH7b/yA=",0) -> #VALUE! | AH1: =AND(JavaSpring_Syllabus!A7,"AAAAAH7b/yE=") -> #VALUE! | AI1: =AND(JavaSpring_Syllabus!B7,"AAAAAH7b/yI=") -> #VALUE! | AJ1: =AND(JavaSpring_Syllabus!C7,"AAAAAH7b/yM=") -> #VALUE! | AK1: =AND(JavaSpring_Syllabus!D7,"AAAAAH7b/yQ=") -> #VALUE! | AL1: =AND(JavaSpring_Syllabus!E7,"AAAAAH7b/yU=") -> #VALUE! | AM1: =AND(JavaSpring_Syllabus!#REF!,"AAAAAH7b/yY=") -> #ERROR! | AN1: =AND(JavaSpring_Syllabus!#REF!,"AAAAAH7b/yc=") -> #ERROR! | AO1: =IF(JavaSpring_Syllabus!8:8,"AAAAAH7b/yg=",0) -> #VALUE! | AP1: =AND(JavaSpring_Syllabus!A8,"AAAAAH7b/yk=") -> #VALUE! | AQ1: =AND(JavaSpring_Syllabus!B8,"AAAAAH7b/yo=") -> #VALUE! | AR1: =AND(JavaSpring_Syllabus!C8,"AAAAAH7b/ys=") -> #VALUE! | AS1: =AND(JavaSpring_Syllabus!D8,"AAAAAH7b/yw=") -> #VALUE! | AT1: =AND(JavaSpring_Syllabus!E8,"AAAAAH7b/y0=") -> #VALUE! | AU1: =AND(JavaSpring_Syllabus!#REF!,"AAAAAH7b/y4=") -> #ERROR! | AV1: =AND(JavaSpring_Syllabus!#REF!,"AAAAAH7b/y8=") -> #ERROR! | AW1: =IF(JavaSpring_Syllabus!11:11,"AAAAAH7b/zA=",0) -> #VALUE! | AX1: =AND(JavaSpring_Syllabus!A11,"AAAAAH7b/zE=") -> #VALUE! | AY1: =AND(JavaSpring_Syllabus!B11,"AAAAAH7b/zI=") -> #VALUE! | AZ1: =AND(JavaSpring_Syllabus!C11,"AAAAAH7b/zM=") -> #VALUE! | BA1: =AND(JavaSpring_Syllabus!D11,"AAAAAH7b/zQ=") -> #VALUE! | BB1: =AND(JavaSpring_Syllabus!E11,"AAAAAH7b/zU=") -> #VALUE! | BC1: =AND(JavaSpring_Syllabus!#REF!,"AAAAAH7b/zY=") -> #ERROR! | BD1: =AND(JavaSpring_Syllabus!#REF!,"AAAAAH7b/zc=") -> #ERROR! | BE1: =IF(JavaSpring_Syllabus!13:13,"AAAAAH7b/zg=",0) -> #VALUE! | BF1: =AND(JavaSpring_Syllabus!A13,"AAAAAH7b/zk=") -> #VALUE! | BG1: =AND(JavaSpring_Syllabus!B13,"AAAAAH7b/zo=") -> #VALUE! | BH1: =AND(JavaSpring_Syllabus!C13,"AAAAAH7b/zs=") -> #VALUE! | BI1: =AND(JavaSpring_Syllabus!D13,"AAAAAH7b/zw=") -> #VALUE! | BJ1: =AND(JavaSpring_Syllabus!E13,"AAAAAH7b/z0=") -> #VALUE! | BK1: =AND(JavaSpring_Syllabus!#REF!,"AAAAAH7b/z4=") -> #ERROR! | BL1: =AND(JavaSpring_Syllabus!#REF!,"AAAAAH7b/z8=") -> #ERROR! | BM1: =IF(JavaSpring_Syllabus!14:14,"AAAAAH7b/0A=",0) -> #VALUE! | BN1: =AND(JavaSpring_Syllabus!A14,"AAAAAH7b/0E=") -> #VALUE! | BO1: =AND(JavaSpring_Syllabus!B14,"AAAAAH7b/0I=") -> #VALUE! | BP1: =AND(JavaSpring_Syllabus!C14,"AAAAAH7b/0M=") -> #VALUE! | BQ1: =AND(JavaSpring_Syllabus!D14,"AAAAAH7b/0Q=") -> #VALUE! | BR1: =AND(JavaSpring_Syllabus!E14,"AAAAAH7b/0U=") -> #VALUE! | BS1: =AND(JavaSpring_Syllabus!#REF!,"AAAAAH7b/0Y=") -> #ERROR! | BT1: =AND(JavaSpring_Syllabus!#REF!,"AAAAAH7b/0c=") -> #ERROR! | BU1: =IF(_xlfn.SINGLE(JavaSpring_Syllabus!#REF!),"AAAAAH7b/0g=",0) -> #ERROR! | BV1: =AND(JavaSpring_Syllabus!#REF!,"AAAAAH7b/0k=") -> #ERROR! | BW1: =AND(JavaSpring_Syllabus!#REF!,"AAAAAH7b/0o=") -> #ERROR! | BX1: =AND(JavaSpring_Syllabus!#REF!,"AAAAAH7b/0s=") -> #ERROR! | BY1: =AND(JavaSpring_Syllabus!#REF!,"AAAAAH7b/0w=") -> #ERROR! | BZ1: =AND(JavaSpring_Syllabus!#REF!,"AAAAAH7b/00=") -> #ERROR! | CA1: =AND(JavaSpring_Syllabus!#REF!,"AAAAAH7b/04=") -> #ERROR! | CB1: =AND(JavaSpring_Syllabus!#REF!,"AAAAAH7b/08=") -> #ERROR! | CC1: =IF(JavaSpring_Syllabus!20:20,"AAAAAH7b/1A=",0) -> #VALUE! | CD1: =AND(JavaSpring_Syllabus!A20,"AAAAAH7b/1E=") -> #VALUE! | CE1: =AND(JavaSpring_Syllabus!B20,"AAAAAH7b/1I=") -> #VALUE! | CF1: =AND(JavaSpring_Syllabus!#REF!,"AAAAAH7b/1M=") -> #ERROR! | CG1: =AND(JavaSpring_Syllabus!#REF!,"AAAAAH7b/1Q=") -> #ERROR! | CH1: =AND(JavaSpring_Syllabus!E20,"AAAAAH7b/1U=") -> #VALUE! | CI1: =AND(JavaSpring_Syllabus!#REF!,"AAAAAH7b/1Y=") -> #ERROR! | CJ1: =AND(JavaSpring_Syllabus!#REF!,"AAAAAH7b/1c=") -> #ERROR! | CK1: =IF(JavaSpring_Syllabus!35:35,"AAAAAH7b/1g=",0) -> #VALUE! | CL1: =AND(JavaSpring_Syllabus!A34,"AAAAAH7b/1k=") -> #VALUE! | CM1: =AND(JavaSpring_Syllabus!B34,"AAAAAH7b/1o=") -> #VALUE! | CN1: =AND(JavaSpring_Syllabus!C35,"AAAAAH7b/1s=") -> #VALUE! | CO1: =AND(JavaSpring_Syllabus!D35,"AAAAAH7b/1w=") -> #VALUE! | CP1: =AND(JavaSpring_Syllabus!E35,"AAAAAH7b/10=") -> #VALUE! | CQ1: =AND(JavaSpring_Syllabus!#REF!,"AAAAAH7b/14=") -> #ERROR! | CR1: =AND(JavaSpring_Syllabus!#REF!,"AAAAAH7b/18=") -> #ERROR! | CS1: =IF(JavaSpring_Syllabus!42:42,"AAAAAH7b/2A=",0) -> #VALUE! | CT1: =AND(JavaSpring_Syllabus!A42,"AAAAAH7b/2E=") -> #VALUE! | CU1: =AND(JavaSpring_Syllabus!B42,"AAAAAH7b/2I=") -> #VALUE! | CV1: =AND(JavaSpring_Syllabus!C42,"AAAAAH7b/2M=") -> #VALUE! | CW1: =AND(JavaSpring_Syllabus!D42,"AAAAAH7b/2Q=") -> FALSE | CX1: =AND(JavaSpring_Syllabus!E42,"AAAAAH7b/2U=") -> #VALUE! | CY1: =AND(JavaSpring_Syllabus!F42,"AAAAAH7b/2Y=") -> #VALUE! | CZ1: =AND(JavaSpring_Syllabus!#REF!,"AAAAAH7b/2c=") -> #ERROR! | DA1: =IF(JavaSpring_Syllabus!46:46,"AAAAAH7b/2g=",0) -> #VALUE! | DB1: =AND(JavaSpring_Syllabus!A46,"AAAAAH7b/2k=") -> #VALUE! | DC1: =AND(JavaSpring_Syllabus!B46,"AAAAAH7b/2o=") -> #VALUE! | DD1: =AND(JavaSpring_Syllabus!C46,"AAAAAH7b/2s=") -> #VALUE! | DE1: =AND(JavaSpring_Syllabus!D46,"AAAAAH7b/2w=") -> #VALUE! | DF1: =AND(JavaSpring_Syllabus!E46,"AAAAAH7b/20=") -> #VALUE! | DG1: =AND(JavaSpring_Syllabus!#REF!,"AAAAAH7b/24=") -> #ERROR! | DH1: =AND(JavaSpring_Syllabus!#REF!,"AAAAAH7b/28=") -> #ERROR! | DI1: =IF(JavaSpring_Syllabus!47:47,"AAAAAH7b/3A=",0) -> #VALUE! | DJ1: =AND(JavaSpring_Syllabus!A47,"AAAAAH7b/3E=") -> #VALUE! | DK1: =AND(JavaSpring_Syllabus!B47,"AAAAAH7b/3I=") -> #VALUE! | DL1: =AND(JavaSpring_Syllabus!C47,"AAAAAH7b/3M=") -> #VALUE! | DM1: =AND(JavaSpring_Syllabus!D47,"AAAAAH7b/3Q=") -> #VALUE! | DN1: =AND(JavaSpring_Syllabus!E47,"AAAAAH7b/3U=") -> #VALUE! | DO1: =AND(JavaSpring_Syllabus!#REF!,"AAAAAH7b/3Y=") -> #ERROR! | DP1: =AND(JavaSpring_Syllabus!#REF!,"AAAAAH7b/3c=") -> #ERROR! | DQ1: =IF(JavaSpring_Syllabus!48:48,"AAAAAH7b/3g=",0) -> #VALUE! | DR1: =AND(JavaSpring_Syllabus!A48,"AAAAAH7b/3k=") -> #VALUE! | DS1: =AND(JavaSpring_Syllabus!B48,"AAAAAH7b/3o=") -> #VALUE! | DT1: =AND(JavaSpring_Syllabus!C48,"AAAAAH7b/3s=") -> #VALUE! | DU1: =AND(JavaSpring_Syllabus!D48,"AAAAAH7b/3w=") -> FALSE | DV1: =AND(JavaSpring_Syllabus!E48,"AAAAAH7b/30=") -> #VALUE! | DW1: =AND(JavaSpring_Syllabus!#REF!,"AAAAAH7b/34=") -> #ERROR! | DX1: =AND(JavaSpring_Syllabus!#REF!,"AAAAAH7b/38=") -> #ERROR! | DY1: =IF(JavaSpring_Syllabus!49:49,"AAAAAH7b/4A=",0) -> #VALUE! | DZ1: =AND(JavaSpring_Syllabus!A49,"AAAAAH7b/4E=") -> #VALUE! | EA1: =AND(JavaSpring_Syllabus!B49,"AAAAAH7b/4I=") -> #VALUE! | EB1: =AND(JavaSpring_Syllabus!C49,"AAAAAH7b/4M=") -> #VALUE! | EC1: =AND(JavaSpring_Syllabus!D49,"AAAAAH7b/4Q=") -> #VALUE! | ED1: =AND(JavaSpring_Syllabus!E49,"AAAAAH7b/4U=") -> #VALUE! | EE1: =AND(JavaSpring_Syllabus!#REF!,"AAAAAH7b/4Y=") -> #ERROR! | EF1: =AND(JavaSpring_Syllabus!#REF!,"AAAAAH7b/4c=") -> #ERROR! | EG1: =IF(JavaSpring_Syllabus!50:50,"AAAAAH7b/4g=",0) -> #VALUE! | EH1: =AND(JavaSpring_Syllabus!A50,"AAAAAH7b/4k=") -> #VALUE! | EI1: =AND(JavaSpring_Syllabus!B50,"AAAAAH7b/4o=") -> #VALUE! | EJ1: =AND(JavaSpring_Syllabus!C50,"AAAAAH7b/4s=") -> #VALUE! | EK1: =AND(JavaSpring_Syllabus!D50,"AAAAAH7b/4w=") -> #VALUE! | EL1: =AND(JavaSpring_Syllabus!E50,"AAAAAH7b/40=") -> #VALUE! | EM1: =AND(JavaSpring_Syllabus!#REF!,"AAAAAH7b/44=") -> #ERROR! | EN1: =AND(JavaSpring_Syllabus!#REF!,"AAAAAH7b/48=") -> #ERROR! | EO1: =IF(JavaSpring_Syllabus!51:51,"AAAAAH7b/5A=",0) -> #VALUE! | EP1: =AND(JavaSpring_Syllabus!A51,"AAAAAH7b/5E=") -> #VALUE! | EQ1: =AND(JavaSpring_Syllabus!B51,"AAAAAH7b/5I=") -> #VALUE! | ER1: =AND(JavaSpring_Syllabus!C51,"AAAAAH7b/5M=") -> #VALUE! | ES1: =AND(JavaSpring_Syllabus!D51,"AAAAAH7b/5Q=") -> #VALUE! | ET1: =AND(JavaSpring_Syllabus!E51,"AAAAAH7b/5U=") -> #VALUE! | EU1: =AND(JavaSpring_Syllabus!#REF!,"AAAAAH7b/5Y=") -> #ERROR! | EV1: =AND(JavaSpring_Syllabus!#REF!,"AAAAAH7b/5c=") -> #ERROR! | EW1: =IF(JavaSpring_Syllabus!52:52,"AAAAAH7b/5g=",0) -> #VALUE! | EX1: =AND(JavaSpring_Syllabus!A52,"AAAAAH7b/5k=") -> #VALUE! | EY1: =AND(JavaSpring_Syllabus!B52,"AAAAAH7b/5o=") -> #VALUE! | EZ1: =AND(JavaSpring_Syllabus!C52,"AAAAAH7b/5s=") -> #VALUE! | FA1: =AND(JavaSpring_Syllabus!D52,"AAAAAH7b/5w=") -> #VALUE! | FB1: =AND(JavaSpring_Syllabus!E52,"AAAAAH7b/50=") -> #VALUE! | FC1: =AND(JavaSpring_Syllabus!#REF!,"AAAAAH7b/54=") -> #ERROR! | FD1: =AND(JavaSpring_Syllabus!#REF!,"AAAAAH7b/58=") -> #ERROR! | FE1: =IF(JavaSpring_Syllabus!53:53,"AAAAAH7b/6A=",0) -> #VALUE! | FF1: =AND(JavaSpring_Syllabus!A53,"AAAAAH7b/6E=") -> #VALUE! | FG1: =AND(JavaSpring_Syllabus!B53,"AAAAAH7b/6I=") -> #VALUE! | FH1: =AND(JavaSpring_Syllabus!C53,"AAAAAH7b/6M=") -> #VALUE! | FI1: =AND(JavaSpring_Syllabus!D53,"AAAAAH7b/6Q=") -> #VALUE! | FJ1: =AND(JavaSpring_Syllabus!E53,"AAAAAH7b/6U=") -> #VALUE! | FK1: =AND(JavaSpring_Syllabus!#REF!,"AAAAAH7b/6Y=") -> #ERROR! | FL1: =AND(JavaSpring_Syllabus!#REF!,"AAAAAH7b/6c=") -> #ERROR! | FM1: =IF(JavaSpring_Syllabus!54:54,"AAAAAH7b/6g=",0) -> #VALUE! | FN1: =AND(JavaSpring_Syllabus!A54,"AAAAAH7b/6k=") -> #VALUE! | FO1: =AND(JavaSpring_Syllabus!B54,"AAAAAH7b/6o=") -> #VALUE! | FP1: =AND(JavaSpring_Syllabus!C54,"AAAAAH7b/6s=") -> #VALUE! | FQ1: =AND(JavaSpring_Syllabus!D54,"AAAAAH7b/6w=") -> #VALUE! | FR1: =AND(JavaSpring_Syllabus!E54,"AAAAAH7b/60=") -> #VALUE! | FS1: =AND(JavaSpring_Syllabus!#REF!,"AAAAAH7b/64=") -> #ERROR! | FT1: =AND(JavaSpring_Syllabus!#REF!,"AAAAAH7b/68=") -> #ERROR! | FU1: =IF(JavaSpring_Syllabus!55:55,"AAAAAH7b/7A=",0) -> #VALUE! | FV1: =AND(JavaSpring_Syllabus!A55,"AAAAAH7b/7E=") -> #VALUE! | FW1: =AND(JavaSpring_Syllabus!B55,"AAAAAH7b/7I=") -> #VALUE! | FX1: =AND(JavaSpring_Syllabus!C55,"AAAAAH7b/7M=") -> #VALUE! | FY1: =AND(JavaSpring_Syllabus!D55,"AAAAAH7b/7Q=") -> #VALUE! | FZ1: =AND(JavaSpring_Syllabus!E55,"AAAAAH7b/7U=") -> #VALUE! | GA1: =AND(JavaSpring_Syllabus!#REF!,"AAAAAH7b/7Y=") -> #ERROR! | GB1: =AND(JavaSpring_Syllabus!#REF!,"AAAAAH7b/7c=") -> #ERROR! | GC1: =IF(_xlfn.SINGLE(JavaSpring_Syllabus!#REF!),"AAAAAH7b/7g=",0) -> #ERROR! | GD1: =AND(JavaSpring_Syllabus!#REF!,"AAAAAH7b/7k=") -> #ERROR! | GE1: =AND(JavaSpring_Syllabus!#REF!,"AAAAAH7b/7o=") -> #ERROR! | GF1: =AND(JavaSpring_Syllabus!#REF!,"AAAAAH7b/7s=") -> #ERROR! | GG1: =AND(JavaSpring_Syllabus!#REF!,"AAAAAH7b/7w=") -> #ERROR! | GH1: =AND(JavaSpring_Syllabus!#REF!,"AAAAAH7b/70=") -> #ERROR! | GI1: =AND(JavaSpring_Syllabus!#REF!,"AAAAAH7b/74=") -> #ERROR! | GJ1: =AND(JavaSpring_Syllabus!#REF!,"AAAAAH7b/78=") -> #ERROR! | GK1: =IF(JavaSpring_Syllabus!56:56,"AAAAAH7b/8A=",0) -> #VALUE! | GL1: =AND(JavaSpring_Syllabus!A56,"AAAAAH7b/8E=") -> #VALUE! | GM1: =AND(JavaSpring_Syllabus!B56,"AAAAAH7b/8I=") -> #VALUE! | GN1: =AND(JavaSpring_Syllabus!C56,"AAAAAH7b/8M=") -> #VALUE! | GO1: =AND(JavaSpring_Syllabus!D56,"AAAAAH7b/8Q=") -> #VALUE! | GP1: =AND(JavaSpring_Syllabus!E56,"AAAAAH7b/8U=") -> #VALUE! | GQ1: =AND(JavaSpring_Syllabus!#REF!,"AAAAAH7b/8Y=") -> #ERROR! | GR1: =AND(JavaSpring_Syllabus!#REF!,"AAAAAH7b/8c=") -> #ERROR! | GS1: =IF(JavaSpring_Syllabus!58:58,"AAAAAH7b/8g=",0) -> #VALUE! | GT1: =AND(JavaSpring_Syllabus!A58,"AAAAAH7b/8k=") -> #VALUE! | GU1: =AND(JavaSpring_Syllabus!B58,"AAAAAH7b/8o=") -> #VALUE! | GV1: =AND(JavaSpring_Syllabus!C58,"AAAAAH7b/8s=") -> #VALUE! | GW1: =AND(JavaSpring_Syllabus!D58,"AAAAAH7b/8w=") -> #VALUE! | GX1: =AND(JavaSpring_Syllabus!E58,"AAAAAH7b/80=") -> #VALUE! | GY1: =AND(JavaSpring_Syllabus!#REF!,"AAAAAH7b/84=") -> #ERROR! | GZ1: =AND(JavaSpring_Syllabus!#REF!,"AAAAAH7b/88=") -> #ERROR! | HA1: =IF(JavaSpring_Syllabus!59:59,"AAAAAH7b/9A=",0) -> #VALUE! | HB1: =AND(JavaSpring_Syllabus!A59,"AAAAAH7b/9E=") -> #VALUE! | HC1: =AND(JavaSpring_Syllabus!B59,"AAAAAH7b/9I=") -> #VALUE! | HD1: =AND(JavaSpring_Syllabus!C59,"AAAAAH7b/9M=") -> #VALUE! | HE1: =AND(JavaSpring_Syllabus!D59,"AAAAAH7b/9Q=") -> #VALUE! | HF1: =AND(JavaSpring_Syllabus!E59,"AAAAAH7b/9U=") -> #VALUE! | HG1: =AND(JavaSpring_Syllabus!#REF!,"AAAAAH7b/9Y=") -> #ERROR! | HH1: =AND(JavaSpring_Syllabus!#REF!,"AAAAAH7b/9c=") -> #ERROR! | HI1: =IF(JavaSpring_Syllabus!60:60,"AAAAAH7b/9g=",0) -> #VALUE! | HJ1: =AND(JavaSpring_Syllabus!A60,"AAAAAH7b/9k=") -> #VALUE! | HK1: =AND(JavaSpring_Syllabus!B60,"AAAAAH7b/9o=") -> #VALUE! | HL1: =AND(JavaSpring_Syllabus!C60,"AAAAAH7b/9s=") -> #VALUE! | HM1: =AND(JavaSpring_Syllabus!D60,"AAAAAH7b/9w=") -> #VALUE! | HN1: =AND(JavaSpring_Syllabus!E60,"AAAAAH7b/90=") -> #VALUE! | HO1: =AND(JavaSpring_Syllabus!#REF!,"AAAAAH7b/94=") -> #ERROR! | HP1: =AND(JavaSpring_Syllabus!#REF!,"AAAAAH7b/98=") -> #ERROR! | HQ1: =IF(JavaSpring_Syllabus!61:61,"AAAAAH7b/+A=",0) -> #VALUE! | HR1: =AND(JavaSpring_Syllabus!A61,"AAAAAH7b/+E=") -> #VALUE! | HS1: =AND(JavaSpring_Syllabus!B61,"AAAAAH7b/+I=") -> #VALUE! | HT1: =AND(JavaSpring_Syllabus!C61,"AAAAAH7b/+M=") -> #VALUE! | HU1: =AND(JavaSpring_Syllabus!D61,"AAAAAH7b/+Q=") -> #VALUE! | HV1: =AND(JavaSpring_Syllabus!E61,"AAAAAH7b/+U=") -> #VALUE! | HW1: =AND(JavaSpring_Syllabus!#REF!,"AAAAAH7b/+Y=") -> #ERROR! | HX1: =AND(JavaSpring_Syllabus!#REF!,"AAAAAH7b/+c=") -> #ERROR! | HY1: =IF(JavaSpring_Syllabus!62:62,"AAAAAH7b/+g=",0) -> #VALUE! | HZ1: =AND(JavaSpring_Syllabus!A62,"AAAAAH7b/+k=") -> #VALUE! | IA1: =AND(JavaSpring_Syllabus!B62,"AAAAAH7b/+o=") -> #VALUE! | IB1: =AND(JavaSpring_Syllabus!C62,"AAAAAH7b/+s=") -> #VALUE! | IC1: =AND(JavaSpring_Syllabus!D62,"AAAAAH7b/+w=") -> #VALUE! | ID1: =AND(JavaSpring_Syllabus!E62,"AAAAAH7b/+0=") -> #VALUE! | IE1: =AND(JavaSpring_Syllabus!#REF!,"AAAAAH7b/+4=") -> #ERROR! | IF1: =AND(JavaSpring_Syllabus!#REF!,"AAAAAH7b/+8=") -> #ERROR! | IG1: =IF(JavaSpring_Syllabus!63:63,"AAAAAH7b//A=",0) -> #VALUE! | IH1: =AND(JavaSpring_Syllabus!A63,"AAAAAH7b//E=") -> #VALUE! | II1: =AND(JavaSpring_Syllabus!B63,"AAAAAH7b//I=") -> #VALUE! | IJ1: =AND(JavaSpring_Syllabus!C63,"AAAAAH7b//M=") -> #VALUE! | IK1: =AND(JavaSpring_Syllabus!D63,"AAAAAH7b//Q=") -> #VALUE! | IL1: =AND(JavaSpring_Syllabus!E63,"AAAAAH7b//U=") -> #VALUE! | IM1: =AND(JavaSpring_Syllabus!#REF!,"AAAAAH7b//Y=") -> #ERROR! | IN1: =AND(JavaSpring_Syllabus!#REF!,"AAAAAH7b//c=") -> #ERROR! | IO1: =IF(JavaSpring_Syllabus!64:64,"AAAAAH7b//g=",0) -> #VALUE! | IP1: =AND(JavaSpring_Syllabus!A64,"AAAAAH7b//k=") -> #VALUE! | IQ1: =AND(JavaSpring_Syllabus!B64,"AAAAAH7b//o=") -> #VALUE! | IR1: =AND(JavaSpring_Syllabus!C64,"AAAAAH7b//s=") -> #VALUE! | IS1: =AND(JavaSpring_Syllabus!D64,"AAAAAH7b//w=") -> #VALUE! | IT1: =AND(JavaSpring_Syllabus!E64,"AAAAAH7b//0=") -> #VALUE! | IU1: =AND(JavaSpring_Syllabus!#REF!,"AAAAAH7b//4=") -> #ERROR! | IV1: =AND(JavaSpring_Syllabus!#REF!,"AAAAAH7b//8=") -> #ERROR!
A2: =IF(JavaSpring_Syllabus!65:65,"AAAAAH/vfwA=",0) -> 0 | B2: =AND(JavaSpring_Syllabus!A65,"AAAAAH/vfwE=") -> #VALUE! | C2: =AND(JavaSpring_Syllabus!B65,"AAAAAH/vfwI=") -> #VALUE! | D2: =AND(JavaSpring_Syllabus!C65,"AAAAAH/vfwM=") -> #VALUE! | E2: =AND(JavaSpring_Syllabus!D65,"AAAAAH/vfwQ=") -> #VALUE! | F2: =AND(JavaSpring_Syllabus!E65,"AAAAAH/vfwU=") -> #VALUE! | G2: =AND(JavaSpring_Syllabus!#REF!,"AAAAAH/vfwY=") -> #ERROR! | H2: =AND(JavaSpring_Syllabus!#REF!,"AAAAAH/vfwc=") -> #ERROR! | I2: =IF(JavaSpring_Syllabus!66:66,"AAAAAH/vfwg=",0) -> 0 | J2: =AND(JavaSpring_Syllabus!A66,"AAAAAH/vfwk=") -> #VALUE! | K2: =AND(JavaSpring_Syllabus!B66,"AAAAAH/vfwo=") -> #VALUE! | L2: =AND(JavaSpring_Syllabus!C66,"AAAAAH/vfws=") -> #VALUE! | M2: =AND(JavaSpring_Syllabus!D66,"AAAAAH/vfww=") -> #VALUE! | N2: =AND(JavaSpring_Syllabus!E66,"AAAAAH/vfw0=") -> #VALUE! | O2: =AND(JavaSpring_Syllabus!#REF!,"AAAAAH/vfw4=") -> #ERROR! | P2: =AND(JavaSpring_Syllabus!#REF!,"AAAAAH/vfw8=") -> #ERROR! | Q2: =IF(JavaSpring_Syllabus!#REF!,"AAAAAH/vfxA=",0) -> #ERROR! | R2: =IF(JavaSpring_Syllabus!A:A,"AAAAAH/vfxE=",0) -> #VALUE! | S2: =IF(JavaSpring_Syllabus!B:B,"AAAAAH/vfxI=",0) -> 0 | T2: =IF(JavaSpring_Syllabus!C:C,"AAAAAH/vfxM=",0) -> 0 | U2: =IF(JavaSpring_Syllabus!D:D,"AAAAAH/vfxQ=",0) -> 0 | V2: =IF(JavaSpring_Syllabus!E:E,"AAAAAH/vfxU=",0) -> 0 | W2: =IF(_xlfn.SINGLE(JavaSpring_Syllabus!#REF!),"AAAAAH/vfxY=",0) -> #ERROR! | X2: =IF(_xlfn.SINGLE(JavaSpring_Syllabus!#REF!),"AAAAAH/vfxc=",0) -> #ERROR! | Y2: =IF(#REF!,"AAAAAH/vfxg=",0) -> #REF! | Z2: =AND(#REF!,"AAAAAH/vfxk=") -> #REF! | AA2: =AND(#REF!,"AAAAAH/vfxo=") -> #REF! | AB2: =AND(#REF!,"AAAAAH/vfxs=") -> #REF! | AC2: =AND(#REF!,"AAAAAH/vfxw=") -> #REF! | AD2: =AND(#REF!,"AAAAAH/vfx0=") -> #REF! | AE2: =AND(#REF!,"AAAAAH/vfx4=") -> #REF! | AF2: =IF(#REF!,"AAAAAH/vfx8=",0) -> #REF! | AG2: =AND(#REF!,"AAAAAH/vfyA=") -> #REF! | AH2: =AND(#REF!,"AAAAAH/vfyE=") -> #REF! | AI2: =AND(#REF!,"AAAAAH/vfyI=") -> #REF! | AJ2: =AND(#REF!,"AAAAAH/vfyM=") -> #REF! | AK2: =AND(#REF!,"AAAAAH/vfyQ=") -> #REF! | AL2: =AND(#REF!,"AAAAAH/vfyU=") -> #REF! | AM2: =IF(#REF!,"AAAAAH/vfyY=",0) -> #REF! | AN2: =AND(#REF!,"AAAAAH/vfyc=") -> #REF! | AO2: =AND(#REF!,"AAAAAH/vfyg=") -> #REF! | AP2: =AND(#REF!,"AAAAAH/vfyk=") -> #REF! | AQ2: =AND(#REF!,"AAAAAH/vfyo=") -> #REF! | AR2: =AND(#REF!,"AAAAAH/vfys=") -> #REF! | AS2: =AND(#REF!,"AAAAAH/vfyw=") -> #REF! | AT2: =IF(#REF!,"AAAAAH/vfy0=",0) -> #REF! | AU2: =AND(#REF!,"AAAAAH/vfy4=") -> #REF! | AV2: =AND(#REF!,"AAAAAH/vfy8=") -> #REF! | AW2: =AND(#REF!,"AAAAAH/vfzA=") -> #REF! | AX2: =AND(#REF!,"AAAAAH/vfzE=") -> #REF! | AY2: =AND(#REF!,"AAAAAH/vfzI=") -> #REF! | AZ2: =AND(#REF!,"AAAAAH/vfzM=") -> #REF! | BA2: =IF(#REF!,"AAAAAH/vfzQ=",0) -> #REF! | BB2: =AND(#REF!,"AAAAAH/vfzU=") -> #REF! | BC2: =AND(#REF!,"AAAAAH/vfzY=") -> #REF! | BD2: =AND(#REF!,"AAAAAH/vfzc=") -> #REF! | BE2: =AND(#REF!,"AAAAAH/vfzg=") -> #REF! | BF2: =AND(#REF!,"AAAAAH/vfzk=") -> #REF! | BG2: =AND(#REF!,"AAAAAH/vfzo=") -> #REF! | BH2: =IF(#REF!,"AAAAAH/vfzs=",0) -> #REF! | BI2: =AND(#REF!,"AAAAAH/vfzw=") -> #REF! | BJ2: =AND(#REF!,"AAAAAH/vfz0=") -> #REF! | BK2: =AND(#REF!,"AAAAAH/vfz4=") -> #REF! | BL2: =AND(#REF!,"AAAAAH/vfz8=") -> #REF! | BM2: =AND(#REF!,"AAAAAH/vf0A=") -> #REF! | BN2: =AND(#REF!,"AAAAAH/vf0E=") -> #REF! | BO2: =IF(#REF!,"AAAAAH/vf0I=",0) -> #REF! | BP2: =AND(#REF!,"AAAAAH/vf0M=") -> #REF! | BQ2: =AND(#REF!,"AAAAAH/vf0Q=") -> #REF! | BR2: =AND(#REF!,"AAAAAH/vf0U=") -> #REF! | BS2: =AND(#REF!,"AAAAAH/vf0Y=") -> #REF! | BT2: =AND(#REF!,"AAAAAH/vf0c=") -> #REF! | BU2: =AND(#REF!,"AAAAAH/vf0g=") -> #REF! | BV2: =IF(#REF!,"AAAAAH/vf0k=",0) -> #REF! | BW2: =AND(#REF!,"AAAAAH/vf0o=") -> #REF! | BX2: =AND(#REF!,"AAAAAH/vf0s=") -> #REF! | BY2: =AND(#REF!,"AAAAAH/vf0w=") -> #REF! | BZ2: =AND(#REF!,"AAAAAH/vf00=") -> #REF! | CA2: =AND(#REF!,"AAAAAH/vf04=") -> #REF! | CB2: =AND(#REF!,"AAAAAH/vf08=") -> #REF! | CC2: =IF(#REF!,"AAAAAH/vf1A=",0) -> #REF! | CD2: =AND(#REF!,"AAAAAH/vf1E=") -> #REF! | CE2: =AND(#REF!,"AAAAAH/vf1I=") -> #REF! | CF2: =AND(#REF!,"AAAAAH/vf1M=") -> #REF! | CG2: =AND(#REF!,"AAAAAH/vf1Q=") -> #REF! | CH2: =AND(#REF!,"AAAAAH/vf1U=") -> #REF! | CI2: =AND(#REF!,"AAAAAH/vf1Y=") -> #REF! | CJ2: =IF(#REF!,"AAAAAH/vf1c=",0) -> #REF! | CK2: =AND(#REF!,"AAAAAH/vf1g=") -> #REF! | CL2: =AND(#REF!,"AAAAAH/vf1k=") -> #REF! | CM2: =AND(#REF!,"AAAAAH/vf1o=") -> #REF! | CN2: =AND(#REF!,"AAAAAH/vf1s=") -> #REF! | CO2: =AND(#REF!,"AAAAAH/vf1w=") -> #REF! | CP2: =AND(#REF!,"AAAAAH/vf10=") -> #REF! | CQ2: =IF(#REF!,"AAAAAH/vf14=",0) -> #REF! | CR2: =AND(#REF!,"AAAAAH/vf18=") -> #REF! | CS2: =AND(#REF!,"AAAAAH/vf2A=") -> #REF! | CT2: =AND(#REF!,"AAAAAH/vf2E=") -> #REF! | CU2: =AND(#REF!,"AAAAAH/vf2I=") -> #REF! | CV2: =AND(#REF!,"AAAAAH/vf2M=") -> #REF! | CW2: =AND(#REF!,"AAAAAH/vf2Q=") -> #REF! | CX2: =IF(#REF!,"AAAAAH/vf2U=",0) -> #REF! | CY2: =AND(#REF!,"AAAAAH/vf2Y=") -> #REF! | CZ2: =AND(#REF!,"AAAAAH/vf2c=") -> #REF! | DA2: =AND(#REF!,"AAAAAH/vf2g=") -> #REF! | DB2: =AND(#REF!,"AAAAAH/vf2k=") -> #REF! | DC2: =AND(#REF!,"AAAAAH/vf2o=") -> #REF! | DD2: =AND(#REF!,"AAAAAH/vf2s=") -> #REF! | DE2: =IF(#REF!,"AAAAAH/vf2w=",0) -> #REF! | DF2: =AND(#REF!,"AAAAAH/vf20=") -> #REF! | DG2: =AND(#REF!,"AAAAAH/vf24=") -> #REF! | DH2: =AND(#REF!,"AAAAAH/vf28=") -> #REF! | DI2: =AND(#REF!,"AAAAAH/vf3A=") -> #REF! | DJ2: =AND(#REF!,"AAAAAH/vf3E=") -> #REF! | DK2: =AND(#REF!,"AAAAAH/vf3I=") -> #REF! | DL2: =IF(#REF!,"AAAAAH/vf3M=",0) -> #REF! | DM2: =AND(#REF!,"AAAAAH/vf3Q=") -> #REF! | DN2: =AND(#REF!,"AAAAAH/vf3U=") -> #REF! | DO2: =AND(#REF!,"AAAAAH/vf3Y=") -> #REF! | DP2: =AND(#REF!,"AAAAAH/vf3c=") -> #REF! | DQ2: =AND(#REF!,"AAAAAH/vf3g=") -> #REF! | DR2: =AND(#REF!,"AAAAAH/vf3k=") -> #REF! | DS2: =IF(#REF!,"AAAAAH/vf3o=",0) -> #REF! | DT2: =AND(#REF!,"AAAAAH/vf3s=") -> #REF! | DU2: =AND(#REF!,"AAAAAH/vf3w=") -> #REF! | DV2: =AND(#REF!,"AAAAAH/vf30=") -> #REF! | DW2: =AND(#REF!,"AAAAAH/vf34=") -> #REF! | DX2: =AND(#REF!,"AAAAAH/vf38=") -> #REF! | DY2: =AND(#REF!,"AAAAAH/vf4A=") -> #REF! | DZ2: =IF(#REF!,"AAAAAH/vf4E=",0) -> #REF! | EA2: =AND(#REF!,"AAAAAH/vf4I=") -> #REF! | EB2: =AND(#REF!,"AAAAAH/vf4M=") -> #REF! | EC2: =AND(#REF!,"AAAAAH/vf4Q=") -> #REF! | ED2: =AND(#REF!,"AAAAAH/vf4U=") -> #REF! | EE2: =AND(#REF!,"AAAAAH/vf4Y=") -> #REF! | EF2: =AND(#REF!,"AAAAAH/vf4c=") -> #REF! | EG2: =IF(#REF!,"AAAAAH/vf4g=",0) -> #REF! | EH2: =AND(#REF!,"AAAAAH/vf4k=") -> #REF! | EI2: =AND(#REF!,"AAAAAH/vf4o=") -> #REF! | EJ2: =AND(#REF!,"AAAAAH/vf4s=") -> #REF! | EK2: =AND(#REF!,"AAAAAH/vf4w=") -> #REF! | EL2: =AND(#REF!,"AAAAAH/vf40=") -> #REF! | EM2: =AND(#REF!,"AAAAAH/vf44=") -> #REF! | EN2: =IF(#REF!,"AAAAAH/vf48=",0) -> #REF! | EO2: =AND(#REF!,"AAAAAH/vf5A=") -> #REF! | EP2: =AND(#REF!,"AAAAAH/vf5E=") -> #REF! | EQ2: =AND(#REF!,"AAAAAH/vf5I=") -> #REF! | ER2: =AND(#REF!,"AAAAAH/vf5M=") -> #REF! | ES2: =AND(#REF!,"AAAAAH/vf5Q=") -> #REF! | ET2: =AND(#REF!,"AAAAAH/vf5U=") -> #REF! | EU2: =IF(#REF!,"AAAAAH/vf5Y=",0) -> #REF! | EV2: =AND(#REF!,"AAAAAH/vf5c=") -> #REF! | EW2: =AND(#REF!,"AAAAAH/vf5g=") -> #REF! | EX2: =AND(#REF!,"AAAAAH/vf5k=") -> #REF! | EY2: =AND(#REF!,"AAAAAH/vf5o=") -> #REF! | EZ2: =AND(#REF!,"AAAAAH/vf5s=") -> #REF! | FA2: =AND(#REF!,"AAAAAH/vf5w=") -> #REF! | FB2: =IF(#REF!,"AAAAAH/vf50=",0) -> #REF! | FC2: =AND(#REF!,"AAAAAH/vf54=") -> #REF! | FD2: =AND(#REF!,"AAAAAH/vf58=") -> #REF! | FE2: =AND(#REF!,"AAAAAH/vf6A=") -> #REF! | FF2: =AND(#REF!,"AAAAAH/vf6E=") -> #REF! | FG2: =AND(#REF!,"AAAAAH/vf6I=") -> #REF! | FH2: =AND(#REF!,"AAAAAH/vf6M=") -> #REF! | FI2: =IF(#REF!,"AAAAAH/vf6Q=",0) -> #REF! | FJ2: =AND(#REF!,"AAAAAH/vf6U=") -> #REF! | FK2: =AND(#REF!,"AAAAAH/vf6Y=") -> #REF! | FL2: =AND(#REF!,"AAAAAH/vf6c=") -> #REF! | FM2: =AND(#REF!,"AAAAAH/vf6g=") -> #REF! | FN2: =AND(#REF!,"AAAAAH/vf6k=") -> #REF! | FO2: =AND(#REF!,"AAAAAH/vf6o=") -> #REF! | FP2: =IF(#REF!,"AAAAAH/vf6s=",0) -> #REF! | FQ2: =AND(#REF!,"AAAAAH/vf6w=") -> #REF! | FR2: =AND(#REF!,"AAAAAH/vf60=") -> #REF! | FS2: =AND(#REF!,"AAAAAH/vf64=") -> #REF! | FT2: =AND(#REF!,"AAAAAH/vf68=") -> #REF! | FU2: =AND(#REF!,"AAAAAH/vf7A=") -> #REF! | FV2: =AND(#REF!,"AAAAAH/vf7E=") -> #REF! | FW2: =IF(#REF!,"AAAAAH/vf7I=",0) -> #REF! | FX2: =AND(#REF!,"AAAAAH/vf7M=") -> #REF! | FY2: =AND(#REF!,"AAAAAH/vf7Q=") -> #REF! | FZ2: =AND(#REF!,"AAAAAH/vf7U=") -> #REF! | GA2: =AND(#REF!,"AAAAAH/vf7Y=") -> #REF! | GB2: =AND(#REF!,"AAAAAH/vf7c=") -> #REF! | GC2: =AND(#REF!,"AAAAAH/vf7g=") -> #REF! | GD2: =IF(#REF!,"AAAAAH/vf7k=",0) -> #REF! | GE2: =AND(#REF!,"AAAAAH/vf7o=") -> #REF! | GF2: =AND(#REF!,"AAAAAH/vf7s=") -> #REF! | GG2: =AND(#REF!,"AAAAAH/vf7w=") -> #REF! | GH2: =AND(#REF!,"AAAAAH/vf70=") -> #REF! | GI2: =AND(#REF!,"AAAAAH/vf74=") -> #REF! | GJ2: =AND(#REF!,"AAAAAH/vf78=") -> #REF! | GK2: =IF(#REF!,"AAAAAH/vf8A=",0) -> #REF! | GL2: =AND(#REF!,"AAAAAH/vf8E=") -> #REF! | GM2: =AND(#REF!,"AAAAAH/vf8I=") -> #REF! | GN2: =AND(#REF!,"AAAAAH/vf8M=") -> #REF! | GO2: =AND(#REF!,"AAAAAH/vf8Q=") -> #REF! | GP2: =AND(#REF!,"AAAAAH/vf8U=") -> #REF! | GQ2: =AND(#REF!,"AAAAAH/vf8Y=") -> #REF! | GR2: =IF(#REF!,"AAAAAH/vf8c=",0) -> #REF! | GS2: =AND(#REF!,"AAAAAH/vf8g=") -> #REF! | GT2: =AND(#REF!,"AAAAAH/vf8k=") -> #REF! | GU2: =AND(#REF!,"AAAAAH/vf8o=") -> #REF! | GV2: =AND(#REF!,"AAAAAH/vf8s=") -> #REF! | GW2: =AND(#REF!,"AAAAAH/vf8w=") -> #REF! | GX2: =AND(#REF!,"AAAAAH/vf80=") -> #REF! | GY2: =IF(#REF!,"AAAAAH/vf84=",0) -> #REF! | GZ2: =AND(#REF!,"AAAAAH/vf88=") -> #REF! | HA2: =AND(#REF!,"AAAAAH/vf9A=") -> #REF! | HB2: =AND(#REF!,"AAAAAH/vf9E=") -> #REF! | HC2: =AND(#REF!,"AAAAAH/vf9I=") -> #REF! | HD2: =AND(#REF!,"AAAAAH/vf9M=") -> #REF! | HE2: =AND(#REF!,"AAAAAH/vf9Q=") -> #REF! | HF2: =IF(#REF!,"AAAAAH/vf9U=",0) -> #REF! | HG2: =AND(#REF!,"AAAAAH/vf9Y=") -> #REF! | HH2: =AND(#REF!,"AAAAAH/vf9c=") -> #REF! | HI2: =AND(#REF!,"AAAAAH/vf9g=") -> #REF! | HJ2: =AND(#REF!,"AAAAAH/vf9k=") -> #REF! | HK2: =AND(#REF!,"AAAAAH/vf9o=") -> #REF! | HL2: =AND(#REF!,"AAAAAH/vf9s=") -> #REF! | HM2: =IF(#REF!,"AAAAAH/vf9w=",0) -> #REF! | HN2: =AND(#REF!,"AAAAAH/vf90=") -> #REF! | HO2: =AND(#REF!,"AAAAAH/vf94=") -> #REF! | HP2: =AND(#REF!,"AAAAAH/vf98=") -> #REF! | HQ2: =AND(#REF!,"AAAAAH/vf+A=") -> #REF! | HR2: =AND(#REF!,"AAAAAH/vf+E=") -> #REF! | HS2: =AND(#REF!,"AAAAAH/vf+I=") -> #REF! | HT2: =IF(#REF!,"AAAAAH/vf+M=",0) -> #REF! | HU2: =AND(#REF!,"AAAAAH/vf+Q=") -> #REF! | HV2: =AND(#REF!,"AAAAAH/vf+U=") -> #REF! | HW2: =AND(#REF!,"AAAAAH/vf+Y=") -> #REF! | HX2: =AND(#REF!,"AAAAAH/vf+c=") -> #REF! | HY2: =AND(#REF!,"AAAAAH/vf+g=") -> #REF! | HZ2: =AND(#REF!,"AAAAAH/vf+k=") -> #REF! | IA2: =IF(#REF!,"AAAAAH/vf+o=",0) -> #REF! | IB2: =AND(#REF!,"AAAAAH/vf+s=") -> #REF! | IC2: =AND(#REF!,"AAAAAH/vf+w=") -> #REF! | ID2: =AND(#REF!,"AAAAAH/vf+0=") -> #REF! | IE2: =AND(#REF!,"AAAAAH/vf+4=") -> #REF! | IF2: =AND(#REF!,"AAAAAH/vf+8=") -> #REF! | IG2: =AND(#REF!,"AAAAAH/vf/A=") -> #REF! | IH2: =IF(#REF!,"AAAAAH/vf/E=",0) -> #REF! | II2: =AND(#REF!,"AAAAAH/vf/I=") -> #REF! | IJ2: =AND(#REF!,"AAAAAH/vf/M=") -> #REF! | IK2: =AND(#REF!,"AAAAAH/vf/Q=") -> #REF! | IL2: =AND(#REF!,"AAAAAH/vf/U=") -> #REF! | IM2: =AND(#REF!,"AAAAAH/vf/Y=") -> #REF! | IN2: =AND(#REF!,"AAAAAH/vf/c=") -> #REF! | IO2: =IF(#REF!,"AAAAAH/vf/g=",0) -> #REF! | IP2: =AND(#REF!,"AAAAAH/vf/k=") -> #REF! | IQ2: =AND(#REF!,"AAAAAH/vf/o=") -> #REF! | IR2: =AND(#REF!,"AAAAAH/vf/s=") -> #REF! | IS2: =AND(#REF!,"AAAAAH/vf/w=") -> #REF! | IT2: =AND(#REF!,"AAAAAH/vf/0=") -> #REF! | IU2: =AND(#REF!,"AAAAAH/vf/4=") -> #REF! | IV2: =IF(#REF!,"AAAAAH/vf/8=",0) -> #REF!
A3: =AND(#REF!,"AAAAABPz/wA=") -> #REF! | B3: =AND(#REF!,"AAAAABPz/wE=") -> #REF! | C3: =AND(#REF!,"AAAAABPz/wI=") -> #REF! | D3: =AND(#REF!,"AAAAABPz/wM=") -> #REF! | E3: =AND(#REF!,"AAAAABPz/wQ=") -> #REF! | F3: =AND(#REF!,"AAAAABPz/wU=") -> #REF! | G3: =IF(#REF!,"AAAAABPz/wY=",0) -> #REF! | H3: =AND(#REF!,"AAAAABPz/wc=") -> #REF! | I3: =AND(#REF!,"AAAAABPz/wg=") -> #REF! | J3: =AND(#REF!,"AAAAABPz/wk=") -> #REF! | K3: =AND(#REF!,"AAAAABPz/wo=") -> #REF! | L3: =AND(#REF!,"AAAAABPz/ws=") -> #REF! | M3: =AND(#REF!,"AAAAABPz/ww=") -> #REF! | N3: =IF(#REF!,"AAAAABPz/w0=",0) -> #REF! | O3: =AND(#REF!,"AAAAABPz/w4=") -> #REF! | P3: =AND(#REF!,"AAAAABPz/w8=") -> #REF! | Q3: =AND(#REF!,"AAAAABPz/xA=") -> #REF! | R3: =AND(#REF!,"AAAAABPz/xE=") -> #REF! | S3: =AND(#REF!,"AAAAABPz/xI=") -> #REF! | T3: =AND(#REF!,"AAAAABPz/xM=") -> #REF! | U3: =IF(#REF!,"AAAAABPz/xQ=",0) -> #REF! | V3: =AND(#REF!,"AAAAABPz/xU=") -> #REF! | W3: =AND(#REF!,"AAAAABPz/xY=") -> #REF! | X3: =AND(#REF!,"AAAAABPz/xc=") -> #REF! | Y3: =AND(#REF!,"AAAAABPz/xg=") -> #REF! | Z3: =AND(#REF!,"AAAAABPz/xk=") -> #REF! | AA3: =AND(#REF!,"AAAAABPz/xo=") -> #REF! | AB3: =IF(#REF!,"AAAAABPz/xs=",0) -> #REF! | AC3: =AND(#REF!,"AAAAABPz/xw=") -> #REF! | AD3: =AND(#REF!,"AAAAABPz/x0=") -> #REF! | AE3: =AND(#REF!,"AAAAABPz/x4=") -> #REF! | AF3: =AND(#REF!,"AAAAABPz/x8=") -> #REF! | AG3: =AND(#REF!,"AAAAABPz/yA=") -> #REF! | AH3: =AND(#REF!,"AAAAABPz/yE=") -> #REF! | AI3: =IF(#REF!,"AAAAABPz/yI=",0) -> #REF! | AJ3: =AND(#REF!,"AAAAABPz/yM=") -> #REF! | AK3: =AND(#REF!,"AAAAABPz/yQ=") -> #REF! | AL3: =AND(#REF!,"AAAAABPz/yU=") -> #REF! | AM3: =AND(#REF!,"AAAAABPz/yY=") -> #REF! | AN3: =AND(#REF!,"AAAAABPz/yc=") -> #REF! | AO3: =AND(#REF!,"AAAAABPz/yg=") -> #REF! | AP3: =IF(#REF!,"AAAAABPz/yk=",0) -> #REF! | AQ3: =AND(#REF!,"AAAAABPz/yo=") -> #REF! | AR3: =AND(#REF!,"AAAAABPz/ys=") -> #REF! | AS3: =AND(#REF!,"AAAAABPz/yw=") -> #REF! | AT3: =AND(#REF!,"AAAAABPz/y0=") -> #REF! | AU3: =AND(#REF!,"AAAAABPz/y4=") -> #REF! | AV3: =AND(#REF!,"AAAAABPz/y8=") -> #REF! | AW3: =IF(#REF!,"AAAAABPz/zA=",0) -> #REF! | AX3: =AND(#REF!,"AAAAABPz/zE=") -> #REF! | AY3: =AND(#REF!,"AAAAABPz/zI=") -> #REF! | AZ3: =AND(#REF!,"AAAAABPz/zM=") -> #REF! | BA3: =AND(#REF!,"AAAAABPz/zQ=") -> #REF! | BB3: =AND(#REF!,"AAAAABPz/zU=") -> #REF! | BC3: =AND(#REF!,"AAAAABPz/zY=") -> #REF! | BD3: =IF(#REF!,"AAAAABPz/zc=",0) -> #REF! | BE3: =AND(#REF!,"AAAAABPz/zg=") -> #REF! | BF3: =AND(#REF!,"AAAAABPz/zk=") -> #REF! | BG3: =AND(#REF!,"AAAAABPz/zo=") -> #REF! | BH3: =AND(#REF!,"AAAAABPz/zs=") -> #REF! | BI3: =AND(#REF!,"AAAAABPz/zw=") -> #REF! | BJ3: =AND(#REF!,"AAAAABPz/z0=") -> #REF! | BK3: =IF(#REF!,"AAAAABPz/z4=",0) -> #REF! | BL3: =AND(#REF!,"AAAAABPz/z8=") -> #REF! | BM3: =AND(#REF!,"AAAAABPz/0A=") -> #REF! | BN3: =AND(#REF!,"AAAAABPz/0E=") -> #REF! | BO3: =AND(#REF!,"AAAAABPz/0I=") -> #REF! | BP3: =AND(#REF!,"AAAAABPz/0M=") -> #REF! | BQ3: =AND(#REF!,"AAAAABPz/0Q=") -> #REF! | BR3: =IF(#REF!,"AAAAABPz/0U=",0) -> #REF! | BS3: =AND(#REF!,"AAAAABPz/0Y=") -> #REF! | BT3: =AND(#REF!,"AAAAABPz/0c=") -> #REF! | BU3: =AND(#REF!,"AAAAABPz/0g=") -> #REF! | BV3: =AND(#REF!,"AAAAABPz/0k=") -> #REF! | BW3: =AND(#REF!,"AAAAABPz/0o=") -> #REF! | BX3: =AND(#REF!,"AAAAABPz/0s=") -> #REF! | BY3: =IF(#REF!,"AAAAABPz/0w=",0) -> #REF! | BZ3: =AND(#REF!,"AAAAABPz/00=") -> #REF! | CA3: =AND(#REF!,"AAAAABPz/04=") -> #REF! | CB3: =AND(#REF!,"AAAAABPz/08=") -> #REF! | CC3: =AND(#REF!,"AAAAABPz/1A=") -> #REF! | CD3: =AND(#REF!,"AAAAABPz/1E=") -> #REF! | CE3: =AND(#REF!,"AAAAABPz/1I=") -> #REF! | CF3: =IF(#REF!,"AAAAABPz/1M=",0) -> #REF! | CG3: =AND(#REF!,"AAAAABPz/1Q=") -> #REF! | CH3: =AND(#REF!,"AAAAABPz/1U=") -> #REF! | CI3: =AND(#REF!,"AAAAABPz/1Y=") -> #REF! | CJ3: =AND(#REF!,"AAAAABPz/1c=") -> #REF! | CK3: =AND(#REF!,"AAAAABPz/1g=") -> #REF! | CL3: =AND(#REF!,"AAAAABPz/1k=") -> #REF! | CM3: =IF(#REF!,"AAAAABPz/1o=",0) -> #REF! | CN3: =AND(#REF!,"AAAAABPz/1s=") -> #REF! | CO3: =AND(#REF!,"AAAAABPz/1w=") -> #REF! | CP3: =AND(#REF!,"AAAAABPz/10=") -> #REF! | CQ3: =AND(#REF!,"AAAAABPz/14=") -> #REF! | CR3: =AND(#REF!,"AAAAABPz/18=") -> #REF! | CS3: =AND(#REF!,"AAAAABPz/2A=") -> #REF! | CT3: =IF(#REF!,"AAAAABPz/2E=",0) -> #REF! | CU3: =AND(#REF!,"AAAAABPz/2I=") -> #REF! | CV3: =AND(#REF!,"AAAAABPz/2M=") -> #REF! | CW3: =AND(#REF!,"AAAAABPz/2Q=") -> #REF! | CX3: =AND(#REF!,"AAAAABPz/2U=") -> #REF! | CY3: =AND(#REF!,"AAAAABPz/2Y=") -> #REF! | CZ3: =AND(#REF!,"AAAAABPz/2c=") -> #REF! | DA3: =IF(#REF!,"AAAAABPz/2g=",0) -> #REF! | DB3: =AND(#REF!,"AAAAABPz/2k=") -> #REF! | DC3: =AND(#REF!,"AAAAABPz/2o=") -> #REF! | DD3: =AND(#REF!,"AAAAABPz/2s=") -> #REF! | DE3: =AND(#REF!,"AAAAABPz/2w=") -> #REF! | DF3: =AND(#REF!,"AAAAABPz/20=") -> #REF! | DG3: =AND(#REF!,"AAAAABPz/24=") -> #REF! | DH3: =IF(#REF!,"AAAAABPz/28=",0) -> #REF! | DI3: =AND(#REF!,"AAAAABPz/3A=") -> #REF! | DJ3: =AND(#REF!,"AAAAABPz/3E=") -> #REF! | DK3: =AND(#REF!,"AAAAABPz/3I=") -> #REF! | DL3: =AND(#REF!,"AAAAABPz/3M=") -> #REF! | DM3: =AND(#REF!,"AAAAABPz/3Q=") -> #REF! | DN3: =AND(#REF!,"AAAAABPz/3U=") -> #REF! | DO3: =IF(#REF!,"AAAAABPz/3Y=",0) -> #REF! | DP3: =AND(#REF!,"AAAAABPz/3c=") -> #REF! | DQ3: =AND(#REF!,"AAAAABPz/3g=") -> #REF! | DR3: =AND(#REF!,"AAAAABPz/3k=") -> #REF! | DS3: =AND(#REF!,"AAAAABPz/3o=") -> #REF! | DT3: =AND(#REF!,"AAAAABPz/3s=") -> #REF! | DU3: =IF(#REF!,"AAAAABPz/3w=",0) -> #REF! | DV3: =IF(#REF!,"AAAAABPz/30=",0) -> #REF! | DW3: =IF(#REF!,"AAAAABPz/34=",0) -> #REF! | DX3: =IF(#REF!,"AAAAABPz/38=",0) -> #REF! | DY3: =IF(#REF!,"AAAAABPz/4A=",0) -> #REF! | DZ3: =IF(#REF!,"AAAAABPz/4E=",0) -> #REF! | EA3: =IF(#REF!,"AAAAABPz/4I=",0) -> #REF! | EB3: =IF('Author and Rec of Changes'!1:1,"AAAAABPz/4M=",0) -> #VALUE! | EC3: =AND('Author and Rec of Changes'!A1,"AAAAABPz/4Q=") -> #VALUE! | ED3: =AND('Author and Rec of Changes'!B1,"AAAAABPz/4U=") -> #VALUE! | EE3: =AND('Author and Rec of Changes'!C1,"AAAAABPz/4Y=") -> #VALUE! | EF3: =AND('Author and Rec of Changes'!E1,"AAAAABPz/4c=") -> #VALUE! | EG3: =AND('Author and Rec of Changes'!F1,"AAAAABPz/4g=") -> #VALUE! | EH3: =AND('Author and Rec of Changes'!G1,"AAAAABPz/4k=") -> #VALUE! | EI3: =IF('Author and Rec of Changes'!#REF!,"AAAAABPz/4o=",0) -> #ERROR! | EJ3: =AND('Author and Rec of Changes'!#REF!,"AAAAABPz/4s=") -> #ERROR! | EK3: =AND('Author and Rec of Changes'!#REF!,"AAAAABPz/4w=") -> #ERROR! | EL3: =AND('Author and Rec of Changes'!#REF!,"AAAAABPz/40=") -> #ERROR! | EM3: =AND('Author and Rec of Changes'!#REF!,"AAAAABPz/44=") -> #ERROR! | EN3: =AND('Author and Rec of Changes'!#REF!,"AAAAABPz/48=") -> #ERROR! | EO3: =AND('Author and Rec of Changes'!#REF!,"AAAAABPz/5A=") -> #ERROR! | EP3: =IF('Author and Rec of Changes'!2:2,"AAAAABPz/5E=",0) -> #VALUE! | EQ3: =AND('Author and Rec of Changes'!A2,"AAAAABPz/5I=") -> #VALUE! | ER3: =AND('Author and Rec of Changes'!B2,"AAAAABPz/5M=") -> #VALUE! | ES3: =AND('Author and Rec of Changes'!C2,"AAAAABPz/5Q=") -> #VALUE! | ET3: =AND('Author and Rec of Changes'!E2,"AAAAABPz/5U=") -> #VALUE! | EU3: =AND('Author and Rec of Changes'!F2,"AAAAABPz/5Y=") -> #VALUE! | EV3: =AND('Author and Rec of Changes'!G2,"AAAAABPz/5c=") -> #VALUE! | EW3: =IF('Author and Rec of Changes'!3:3,"AAAAABPz/5g=",0) -> #VALUE! | EX3: =AND('Author and Rec of Changes'!A3,"AAAAABPz/5k=") -> #VALUE! | EY3: =AND('Author and Rec of Changes'!B3,"AAAAABPz/5o=") -> #VALUE! | EZ3: =AND('Author and Rec of Changes'!C3,"AAAAABPz/5s=") -> #VALUE! | FA3: =AND('Author and Rec of Changes'!E3,"AAAAABPz/5w=") -> #VALUE! | FB3: =AND('Author and Rec of Changes'!F3,"AAAAABPz/50=") -> #VALUE! | FC3: =AND('Author and Rec of Changes'!G3,"AAAAABPz/54=") -> #VALUE! | FD3: =IF('Author and Rec of Changes'!#REF!,"AAAAABPz/58=",0) -> #ERROR! | FE3: =AND('Author and Rec of Changes'!#REF!,"AAAAABPz/6A=") -> #ERROR! | FF3: =AND('Author and Rec of Changes'!#REF!,"AAAAABPz/6E=") -> #ERROR! | FG3: =AND('Author and Rec of Changes'!#REF!,"AAAAABPz/6I=") -> #ERROR! | FH3: =AND('Author and Rec of Changes'!#REF!,"AAAAABPz/6M=") -> #ERROR! | FI3: =AND('Author and Rec of Changes'!#REF!,"AAAAABPz/6Q=") -> #ERROR! | FJ3: =AND('Author and Rec of Changes'!#REF!,"AAAAABPz/6U=") -> #ERROR! | FK3: =IF('Author and Rec of Changes'!#REF!,"AAAAABPz/6Y=",0) -> #ERROR! | FL3: =AND('Author and Rec of Changes'!#REF!,"AAAAABPz/6c=") -> #ERROR! | FM3: =AND('Author and Rec of Changes'!#REF!,"AAAAABPz/6g=") -> #ERROR! | FN3: =AND('Author and Rec of Changes'!#REF!,"AAAAABPz/6k=") -> #ERROR! | FO3: =AND('Author and Rec of Changes'!#REF!,"AAAAABPz/6o=") -> #ERROR! | FP3: =AND('Author and Rec of Changes'!#REF!,"AAAAABPz/6s=") -> #ERROR! | FQ3: =AND('Author and Rec of Changes'!#REF!,"AAAAABPz/6w=") -> #ERROR! | FR3: =IF('Author and Rec of Changes'!4:4,"AAAAABPz/60=",0) -> #VALUE! | FS3: =AND('Author and Rec of Changes'!A4,"AAAAABPz/64=") -> #VALUE! | FT3: =AND('Author and Rec of Changes'!B4,"AAAAABPz/68=") -> #VALUE! | FU3: =AND('Author and Rec of Changes'!C4,"AAAAABPz/7A=") -> #VALUE! | FV3: =AND('Author and Rec of Changes'!E4,"AAAAABPz/7E=") -> #VALUE! | FW3: =AND('Author and Rec of Changes'!F4,"AAAAABPz/7I=") -> #VALUE! | FX3: =AND('Author and Rec of Changes'!G4,"AAAAABPz/7M=") -> #VALUE! | FY3: =IF('Author and Rec of Changes'!#REF!,"AAAAABPz/7Q=",0) -> #ERROR! | FZ3: =AND('Author and Rec of Changes'!#REF!,"AAAAABPz/7U=") -> #ERROR! | GA3: =AND('Author and Rec of Changes'!#REF!,"AAAAABPz/7Y=") -> #ERROR! | GB3: =AND('Author and Rec of Changes'!#REF!,"AAAAABPz/7c=") -> #ERROR! | GC3: =AND('Author and Rec of Changes'!#REF!,"AAAAABPz/7g=") -> #ERROR! | GD3: =AND('Author and Rec of Changes'!#REF!,"AAAAABPz/7k=") -> #ERROR! | GE3: =AND('Author and Rec of Changes'!#REF!,"AAAAABPz/7o=") -> #ERROR! | GF3: =IF('Author and Rec of Changes'!#REF!,"AAAAABPz/7s=",0) -> #ERROR! | GG3: =AND('Author and Rec of Changes'!#REF!,"AAAAABPz/7w=") -> #ERROR! | GH3: =AND('Author and Rec of Changes'!#REF!,"AAAAABPz/70=") -> #ERROR! | GI3: =AND('Author and Rec of Changes'!#REF!,"AAAAABPz/74=") -> #ERROR! | GJ3: =AND('Author and Rec of Changes'!#REF!,"AAAAABPz/78=") -> #ERROR! | GK3: =AND('Author and Rec of Changes'!#REF!,"AAAAABPz/8A=") -> #ERROR! | GL3: =AND('Author and Rec of Changes'!#REF!,"AAAAABPz/8E=") -> #ERROR! | GM3: =IF('Author and Rec of Changes'!#REF!,"AAAAABPz/8I=",0) -> #ERROR! | GN3: =AND('Author and Rec of Changes'!#REF!,"AAAAABPz/8M=") -> #ERROR! | GO3: =AND('Author and Rec of Changes'!#REF!,"AAAAABPz/8Q=") -> #ERROR! | GP3: =AND('Author and Rec of Changes'!#REF!,"AAAAABPz/8U=") -> #ERROR! | GQ3: =AND('Author and Rec of Changes'!#REF!,"AAAAABPz/8Y=") -> #ERROR! | GR3: =AND('Author and Rec of Changes'!#REF!,"AAAAABPz/8c=") -> #ERROR! | GS3: =AND('Author and Rec of Changes'!#REF!,"AAAAABPz/8g=") -> #ERROR! | GT3: =IF('Author and Rec of Changes'!#REF!,"AAAAABPz/8k=",0) -> #ERROR! | GU3: =AND('Author and Rec of Changes'!#REF!,"AAAAABPz/8o=") -> #ERROR! | GV3: =AND('Author and Rec of Changes'!#REF!,"AAAAABPz/8s=") -> #ERROR! | GW3: =AND('Author and Rec of Changes'!#REF!,"AAAAABPz/8w=") -> #ERROR! | GX3: =AND('Author and Rec of Changes'!#REF!,"AAAAABPz/80=") -> #ERROR! | GY3: =AND('Author and Rec of Changes'!#REF!,"AAAAABPz/84=") -> #ERROR! | GZ3: =AND('Author and Rec of Changes'!#REF!,"AAAAABPz/88=") -> #ERROR! | HA3: =IF('Author and Rec of Changes'!#REF!,"AAAAABPz/9A=",0) -> #ERROR! | HB3: =AND('Author and Rec of Changes'!#REF!,"AAAAABPz/9E=") -> #ERROR! | HC3: =AND('Author and Rec of Changes'!#REF!,"AAAAABPz/9I=") -> #ERROR! | HD3: =AND('Author and Rec of Changes'!#REF!,"AAAAABPz/9M=") -> #ERROR! | HE3: =AND('Author and Rec of Changes'!#REF!,"AAAAABPz/9Q=") -> #ERROR! | HF3: =AND('Author and Rec of Changes'!#REF!,"AAAAABPz/9U=") -> #ERROR! | HG3: =AND('Author and Rec of Changes'!#REF!,"AAAAABPz/9Y=") -> #ERROR! | HH3: =IF('Author and Rec of Changes'!#REF!,"AAAAABPz/9c=",0) -> #ERROR! | HI3: =AND('Author and Rec of Changes'!#REF!,"AAAAABPz/9g=") -> #ERROR! | HJ3: =AND('Author and Rec of Changes'!#REF!,"AAAAABPz/9k=") -> #ERROR! | HK3: =AND('Author and Rec of Changes'!#REF!,"AAAAABPz/9o=") -> #ERROR! | HL3: =AND('Author and Rec of Changes'!#REF!,"AAAAABPz/9s=") -> #ERROR! | HM3: =AND('Author and Rec of Changes'!#REF!,"AAAAABPz/9w=") -> #ERROR! | HN3: =AND('Author and Rec of Changes'!#REF!,"AAAAABPz/90=") -> #ERROR! | HO3: =IF('Author and Rec of Changes'!#REF!,"AAAAABPz/94=",0) -> #ERROR! | HP3: =AND('Author and Rec of Changes'!#REF!,"AAAAABPz/98=") -> #ERROR! | HQ3: =AND('Author and Rec of Changes'!#REF!,"AAAAABPz/+A=") -> #ERROR! | HR3: =AND('Author and Rec of Changes'!#REF!,"AAAAABPz/+E=") -> #ERROR! | HS3: =AND('Author and Rec of Changes'!#REF!,"AAAAABPz/+I=") -> #ERROR! | HT3: =AND('Author and Rec of Changes'!#REF!,"AAAAABPz/+M=") -> #ERROR! | HU3: =AND('Author and Rec of Changes'!#REF!,"AAAAABPz/+Q=") -> #ERROR! | HV3: =IF('Author and Rec of Changes'!5:5,"AAAAABPz/+U=",0) -> #VALUE! | HW3: =AND('Author and Rec of Changes'!A5,"AAAAABPz/+Y=") -> #VALUE! | HX3: =AND('Author and Rec of Changes'!B5,"AAAAABPz/+c=") -> #VALUE! | HY3: =AND('Author and Rec of Changes'!C5,"AAAAABPz/+g=") -> #VALUE! | HZ3: =AND('Author and Rec of Changes'!E5,"AAAAABPz/+k=") -> #VALUE! | IA3: =AND('Author and Rec of Changes'!F5,"AAAAABPz/+o=") -> #VALUE! | IB3: =AND('Author and Rec of Changes'!G5,"AAAAABPz/+s=") -> #VALUE! | IC3: =IF('Author and Rec of Changes'!#REF!,"AAAAABPz/+w=",0) -> #ERROR! | ID3: =AND('Author and Rec of Changes'!#REF!,"AAAAABPz/+0=") -> #ERROR! | IE3: =AND('Author and Rec of Changes'!#REF!,"AAAAABPz/+4=") -> #ERROR! | IF3: =AND('Author and Rec of Changes'!#REF!,"AAAAABPz/+8=") -> #ERROR! | IG3: =AND('Author and Rec of Changes'!#REF!,"AAAAABPz//A=") -> #ERROR! | IH3: =AND('Author and Rec of Changes'!#REF!,"AAAAABPz//E=") -> #ERROR! | II3: =AND('Author and Rec of Changes'!#REF!,"AAAAABPz//I=") -> #ERROR! | IJ3: =IF('Author and Rec of Changes'!#REF!,"AAAAABPz//M=",0) -> #ERROR! | IK3: =AND('Author and Rec of Changes'!#REF!,"AAAAABPz//Q=") -> #ERROR! | IL3: =AND('Author and Rec of Changes'!#REF!,"AAAAABPz//U=") -> #ERROR! | IM3: =AND('Author and Rec of Changes'!#REF!,"AAAAABPz//Y=") -> #ERROR! | IN3: =AND('Author and Rec of Changes'!#REF!,"AAAAABPz//c=") -> #ERROR! | IO3: =AND('Author and Rec of Changes'!#REF!,"AAAAABPz//g=") -> #ERROR! | IP3: =AND('Author and Rec of Changes'!#REF!,"AAAAABPz//k=") -> #ERROR! | IQ3: =IF('Author and Rec of Changes'!6:6,"AAAAABPz//o=",0) -> #VALUE! | IR3: =AND('Author and Rec of Changes'!A6,"AAAAABPz//s=") -> #VALUE! | IS3: =AND('Author and Rec of Changes'!B6,"AAAAABPz//w=") -> #VALUE! | IT3: =AND('Author and Rec of Changes'!C6,"AAAAABPz//0=") -> #VALUE! | IU3: =AND('Author and Rec of Changes'!E6,"AAAAABPz//4=") -> #VALUE! | IV3: =AND('Author and Rec of Changes'!F6,"AAAAABPz//8=") -> #VALUE!
A4: =AND('Author and Rec of Changes'!G6,"AAAAAH/rVAA=") -> #VALUE! | B4: =IF('Author and Rec of Changes'!7:7,"AAAAAH/rVAE=",0) -> 0 | C4: =AND('Author and Rec of Changes'!A7,"AAAAAH/rVAI=") -> #VALUE! | D4: =AND('Author and Rec of Changes'!B7,"AAAAAH/rVAM=") -> #VALUE! | E4: =AND('Author and Rec of Changes'!C7,"AAAAAH/rVAQ=") -> #VALUE! | F4: =AND('Author and Rec of Changes'!E7,"AAAAAH/rVAU=") -> #VALUE! | G4: =AND('Author and Rec of Changes'!F7,"AAAAAH/rVAY=") -> #VALUE! | H4: =AND('Author and Rec of Changes'!G7,"AAAAAH/rVAc=") -> #VALUE! | I4: =IF('Author and Rec of Changes'!8:8,"AAAAAH/rVAg=",0) -> 0 | J4: =AND('Author and Rec of Changes'!A8,"AAAAAH/rVAk=") -> #VALUE! | K4: =AND('Author and Rec of Changes'!B8,"AAAAAH/rVAo=") -> #VALUE! | L4: =AND('Author and Rec of Changes'!C8,"AAAAAH/rVAs=") -> #VALUE! | M4: =AND('Author and Rec of Changes'!E8,"AAAAAH/rVAw=") -> #VALUE! | N4: =AND('Author and Rec of Changes'!F8,"AAAAAH/rVA0=") -> #VALUE! | O4: =AND('Author and Rec of Changes'!G8,"AAAAAH/rVA4=") -> #VALUE! | P4: =IF('Author and Rec of Changes'!9:9,"AAAAAH/rVA8=",0) -> 0 | Q4: =AND('Author and Rec of Changes'!A9,"AAAAAH/rVBA=") -> #VALUE! | R4: =AND('Author and Rec of Changes'!B9,"AAAAAH/rVBE=") -> #VALUE! | S4: =AND('Author and Rec of Changes'!C9,"AAAAAH/rVBI=") -> #VALUE! | T4: =AND('Author and Rec of Changes'!E9,"AAAAAH/rVBM=") -> #VALUE! | U4: =AND('Author and Rec of Changes'!F9,"AAAAAH/rVBQ=") -> #VALUE! | V4: =AND('Author and Rec of Changes'!G9,"AAAAAH/rVBU=") -> #VALUE! | W4: =IF('Author and Rec of Changes'!10:10,"AAAAAH/rVBY=",0) -> 0 | X4: =IF('Author and Rec of Changes'!11:11,"AAAAAH/rVBc=",0) -> 0 | Y4: =IF('Author and Rec of Changes'!12:12,"AAAAAH/rVBg=",0) -> 0 | Z4: =IF('Author and Rec of Changes'!13:13,"AAAAAH/rVBk=",0) -> 0 | AA4: =IF('Author and Rec of Changes'!14:14,"AAAAAH/rVBo=",0) -> #VALUE! | AB4: =IF('Author and Rec of Changes'!15:15,"AAAAAH/rVBs=",0) -> #VALUE! | AC4: =IF('Author and Rec of Changes'!16:16,"AAAAAH/rVBw=",0) -> #VALUE! | AD4: =IF('Author and Rec of Changes'!A:A,"AAAAAH/rVB0=",0) -> 0 | AE4: =IF('Author and Rec of Changes'!B:B,"AAAAAH/rVB4=",0) -> #VALUE! | AF4: =IF('Author and Rec of Changes'!C:C,"AAAAAH/rVB8=",0) -> 0 | AG4: =IF('Author and Rec of Changes'!E:E,"AAAAAH/rVCA=",0) -> 0 | AH4: =IF('Author and Rec of Changes'!F:F,"AAAAAH/rVCE=",0) -> 0 | AI4: =IF('Author and Rec of Changes'!G:G,"AAAAAH/rVCI=",0) -> 0 | AJ4: AAAAAH/rVCM= | AK4: AAAAAH/rVCQ= | AL4: AAAAAH/rVCU= | AM4: =IF("N",[0]!_FilterDatabase,"AAAAAH/rVCY=") -> #ERROR!
A5: =AND(JavaSpring_Syllabus!A1,"AAAAACvx+wA=") -> #VALUE! | B5: =IF(JavaSpring_Syllabus!#REF!,"AAAAACvx+wE=",0) -> #ERROR! | C5: =AND(JavaSpring_Syllabus!#REF!,"AAAAACvx+wI=") -> #ERROR! | D5: =AND(JavaSpring_Syllabus!#REF!,"AAAAACvx+wM=") -> #ERROR! | E5: =AND(JavaSpring_Syllabus!#REF!,"AAAAACvx+wQ=") -> #ERROR! | F5: =AND(JavaSpring_Syllabus!#REF!,"AAAAACvx+wU=") -> #ERROR! | G5: =AND(JavaSpring_Syllabus!#REF!,"AAAAACvx+wY=") -> #ERROR! | H5: =AND(JavaSpring_Syllabus!#REF!,"AAAAACvx+wc=") -> #ERROR! | I5: =AND(JavaSpring_Syllabus!#REF!,"AAAAACvx+wg=") -> #ERROR! | J5: =IF(JavaSpring_Syllabus!3:3,"AAAAACvx+wk=",0) -> 0 | K5: =AND(JavaSpring_Syllabus!A3,"AAAAACvx+wo=") -> #VALUE! | L5: =AND(JavaSpring_Syllabus!B3,"AAAAACvx+ws=") -> #VALUE! | M5: =AND(JavaSpring_Syllabus!C3,"AAAAACvx+ww=") -> #VALUE! | N5: =AND(JavaSpring_Syllabus!D3,"AAAAACvx+w0=") -> #VALUE! | O5: =AND(JavaSpring_Syllabus!E3,"AAAAACvx+w4=") -> #VALUE! | P5: =AND(JavaSpring_Syllabus!#REF!,"AAAAACvx+w8=") -> #ERROR! | Q5: =AND(JavaSpring_Syllabus!#REF!,"AAAAACvx+xA=") -> #ERROR!

Sheet Guidelines and Explanation
B1: Guidelines and Explanation
B2: 1. Level of Skills
B4: Level | C4: Name | D4: Description | E4: Level of Skills in QMS
B5: 0 | C5: No experience | D5: The individual with no experience or no understanding to perform the task | E5: 1: Fundamental Awareness
B6: 1 | C6: Basic | D6: The individual demonstrates minimal or no understanding of the competency. Frequent errors or mistakes are made when attempting tasks related to this competency. Significant guidance and supervision are required to perform tasks. Performance consistently falls short of expected standards. | E6: 2: Limited Experience
B7: 2 | C7: Intermediate | D7: The individual possesses basic knowledge and understanding of the competency. Performance is inconsistent, with occasional errors or mistakes. Requires moderate supervision and guidance to perform tasks. Competency is not yet fully developed. | E7: 3: Intermediate
B8: 3 | C8: Advanced | D8: The individual demonstrates a solid understanding of the competency. Performance is generally accurate, with occasional minor errors. Can perform tasks independently with minimal supervision. Meets the expected standards for competency in this area. | E8: 4: Advanced
B9: 4 | C9: Expert | D9: The individual is a subject matter expert in this competency. Exceptional accuracy and efficiency in performing tasks. Demonstrates a deep understanding and can apply knowledge creatively. Able to innovate, solve complex problems, and teach others. | E9: 5: Expert
B11: 2. Skill Priority
B13: Skill Priority | C13: Description
B14: 1 primary skill | C14: The main skill that the course is designed to develop. This skill reflects the core learning objective and the most important outcome learners are expected to achieve after completing the course
B15: No more than 4 secondary skills | C15: Supporting skills that are related to and help reinforce the primary skill. These skills provide additional value to the course but are not the main focus
B18: 3. Current–Future Balance
B20: Stage | C20: Definition
B21: 70% Current Needs | C21: Focuses on the essential skills, tools, and tasks that learners need to perform their current job effectively and meet required standards
B22: 30% Future Needs | C22: Focuses on preparing learners for the next job level or future skill requirements
B24: 4. Bloom's Taxonomy
B26: Level | C26: Descriptions | D26: Verbs (examples) Learning objective ~ Bloom Level = "Verb" + "Content" | E26: Verbs (examples) Learning objective ~ Bloom Level = "Verb" + "Content" | F26: Example Learning Objective
B27: B1-Remember | C27: The ability to Remember previously learned information. Very limited use for Technology company employees; mainly for awareness (Aware) such as policies, standards, or basic terminology. | D27: Nhóm lại, Trình bày, Ghi nhớ, Miêu tả, Kể ra, Sắp đặt, Tìm kiếm, Sắp xếp, Nhận biết, Nhớ lại, Gọi tên, Liệt kê, Sao chép lại, Trích dẫn, Nhắc lại | E27: Group, Present, Recall, Describe, List, Arrange, Search, Sort, Identify, Retrieve, Name, Enumerate, Copy, Cite, Repeat | F27: List the 4 OOP pillars (encapsulation, inheritance, polymorphism, abstraction) and define each term.
B28: B2-Understand | C28: The ability to Explain or Interpret the meaning of information. Low-frequency use, mainly for standard and policy-related topics to ensure alignment (Aligned) to theoretical intent, without requiring independent execution. | D28: Tương phản, Liên kết, Diễn giải cụ thể, Phản biện, So sánh, Trình bày cách hiểu, Ước tính, Phân loại, Lấy ví dụ, Giải thích, Phân biệt, Diễn tả, Chỉ ra, Tìm khác biệt, Kể lại, Nhận định, Miêu tả | E28: Contrast, Link, Explain in detail, Debate, Compare, Interpret, Estimate, Categorize, Give examples, Clarify, Differentiate, Describe, Point out, Distinguish, Recount, Recognize | F28: Explain the difference between an interface and an abstract class in Java, and illustrate with a short code snippet.
B29: B3-Apply | C29: The ability to Use learned knowledge to Perform a task in each situation. Mandatory or high-frequency use for all job description. This is the minimum level where learning becomes executable (Executable) in daily work. | D29: Áp dụng, Chứng minh, Làm ra, Tính toán, Thay đổi, Chuẩn bị, Hoàn thành, Dự đoán, Giải quyết, Sử dụng, Khám phá, Sửa đổi, Vận hành, Minh họa, Thực hiện | E29: Apply, Demonstrate, Produce, Calculate, Modify, Prepare, Complete, Predict, Solve, Use, Explore, Edit, Operate, Illustrate, Execute | F29: Implement/Apply encapsulation by creating a BankAccount class with private fields, public getters/setters (with validation), and use it in a small main() program.
B30: B4-Analyze | C30: The ability to Break information into parts and examine relationships between them. Medium-to-high frequency use for mid-to-senior roles. At this level, work becomes manageable (Manageable) with less supervision and better handling of exceptions. | D30: Thẩm định, Tìm lỗi, Giải thích, Phân loại, Sắp xếp, Phân chia, So sánh, Tính toán, Suy luận, Đối chiếu, Phân biệt, Kiểm tra, Tìm khác biệt, Kết nối, Lựa chọn, Phê bình, Phân tích cấu trúc, Đặt câu hỏi | E30: Evaluate, Identify errors, Explain, Categorize, Organize, Divide, Compare, Compute, Deduce, Cross-check, Differentiate, Inspect, Find differences, Connect, Select, Critique, Analyze structure, Pose questions | F30: Given a small Java project, analyze the class relationships (inheritance vs composition), and identify violations of encapsulation or misuse of inheritance.
B31: B5-Evaluate | C31: The ability to Make Judgments based on defined criteria or standards. Medium-frequency, selective use for senior roles who make decisions and take accountability (Accountable) for outcomes. | D31: Gợi ý, Thẩm định, Đưa ra lựa chọn, Kiểm tra, Tranh luận, Hỗ trợ, Phê bình, So sánh, Chứng minh, Quyết định, Kết luận, Tổng kết, Xếp loại, Thuyết phục, Bảo vệ, Phân biệt, Đặt ưu tiên, Giải thích, Dự đoán, Sửa lỗi | E31: Suggest, Assess, Choose, Test, Debate, Support, Critique, Compare, Prove, Decide, Conclude, Summarize, Rank, Persuade, Defend, Distinguish, Prioritize, Justify, Forecast, Correct | F31: Critique two alternative designs for a Payment module (inheritance-based vs strategy pattern with interfaces) and justify which is more maintainable based on SOLID criteria.
B32: B6-Create | C32: The ability to combine elements to Produce a new or original outcome. Low-frequency, selective use for roles with broader impact, and recognized when results are reusable (Reusable) across teams or projects. | D32: Kết hợp, Tập hợp, Chuẩn bị, Tái sắp xếp, Tạo ra, Viết lại, Xây dựng, Sáng tạo, Giải thích, Thiết kế, Tạo thành công thức, Thay thế, Quản lý, Tích hợp, Khái quát, Phát minh, Cấu trúc hóa, Sửa đổi, Lập kế hoạch | E32: Combine, Assemble, Prepare, Reorganize, Generate, Rewrite, Build, Invent, Explain, Design, Formulate, Replace, Manage, Integrate, Summarize, Innovate, Structure, Revise, Plan | F32: Design and develop a mini “Library Management” system applying OOP (classes, interfaces, polymorphism), including at least one design pattern (e.g., Strategy for fine calculation), and produce runnable code + short design notes (UML optional).
B34: 5. Delivery Type (G collum in <Topic Name>_Schedule)
B36: Delivery Type | C36: English version | D36: Vietnamese version
B37: Concept/Lecture | C37: Trainers deliver lessons: Present theory on a specific topic, often using slides, demonstrations (demo), short exercises, or group activities during teaching. | D37: Giảng viên thực hiện hoạt động giảng dạy: Trình bày lý thuyết của một chủ để chuyên môn, thường sử dụng bài thuyết trình (slides), bài thử nghiệm (demo), bài tập ngắn hoặc bào tập nhóm trong quá trình giảng dạy.
B38: Assignment/Lab | C38: Learners practice on their own, complete assignments or lab exercises to reinforce or apply the knowledge learned. | D38: Học viên tự thực hành, làm bài tập/bài Labs nhằm củng cố/vận dụng kiến thức đã học.
B39: Guides/ Review | C39: Trainers check work results and observe how learners perform tasks; give feedback, scores, and comments based on set criteria; guide improvements for individuals/team | D39: Người hướng dẫn xem xét kết quả bài làm và quá trình thực hiện của học viên; đưa nhận xét, chấm/đánh giá theo tiêu chí và hướng dẫn cải thiện theo cá nhân hoặc theo nhóm đối với các bài tập/bài kiểm tra được giao.
B40: Test /Quiz | C40: Short tests or quizzes for each lesson/topic to assess learners’ understanding; may be done during the learning process or after finishing a module. | D40: Hoạt động kiểm tra ngắn theo bài/chuyên đề nhằm đánh giá mức độ nắm kiến thức theo từng phần nội dung, có thể thực hiện theo thời lượng học hoặc sau khi hoàn thành một module
B41: Exam | C41: Final exam for each course, to evaluate the contents learned, including previous assignments and tests. | D41: Bài thi cuối khóa/cuối kỳ để đánh giá tổng hợp mức độ đạt mục tiêu học tập của khóa học/module; có thể bao gồm lý thuyết và thực hành, dựa trên các nội dung đã học.
B42: Workshop/Seminar | C42: Discussion or sharing sessions: Focus on discussion, case-based practice, answering questions, and clarifying professional content between trainers/guest speakers and learners. | D42: Buổi trao đổi/chia sẻ chuyên đề: tập trung thảo luận, thực hành theo tình huống, giải đáp thắc mắc và làm rõ nội dung chuyên môn giữa giảng viên/khách mời và học viên.
B43: Class Meeting | C43: Class sessions to explain course rules, assignments, and learners’ responsibilities. | D43: Buổi sinh hoạt lớp: giữa quản lý lớp/giảng viên chủ nhiệm và học viên nhằm kiểm tra tiến độ học tập, nhắc nhở quy định, trao đổi vấn đề học vụ và thông báo các cập nhật liên quan đến lớp/khóa học
B44: Self-learning | C44: Learners study materials independently (e.g., e-learning courses, documents, videos) without direct trainer facilitation | D44: Học viên tự học thông qua các tài liệu (ví dụ: khóa học e-learning, tài liệu, video) mà không có sự hướng dẫn trực tiếp từ giảng viên
B45: Sightseeing and other outdoor activities | C45: Extracurricular activities are often used in the Corporate Culture module | D45: Hoạt động ngoại khóa: tham quan/hoạt động ngoài trời phục vụ mục tiêu trải nghiệm (thường dùng trong học phần Văn hóa doanh nghiệp hoặc gắn kết đội nhóm).
B47: 6. Training Format
B49: Training format | C49: English version | D49: Vietnamese version
B50: Online | C50: Learners study materials independently (e.g., e-learning courses, documents, videos) without direct trainer facilitation | D50: Học viên tự học thông qua các tài liệu (ví dụ: khóa học e-learning, tài liệu, video) mà không có sự hướng dẫn trực tiếp từ giảng viên
B51: Offline | C51: Learners attend in-person training sessions at a physical location with direct interaction with trainers and peers | D51: Học viên tham gia đào tạo trực tiếp tại địa điểm cụ thể, có sự tương tác trực tiếp với giảng viên và các học viên khác
B52: Vitual | C52: Learners participate in live online training sessions via virtual platforms, with real-time interaction with trainers and peers | D52: Học viên tham gia các buổi đào tạo trực tuyến trực tiếp thông qua nền tảng online, có tương tác thời gian thực với giảng viên và các học viên khác
B53: Hybrid | C53: Learners participate in a combination of virtual (live online) and offline (in-person) training, combining real-time online interaction with face-to-face sessions | D53: Học viên tham gia kết hợp giữa đào tạo trực tuyến trực tiếp (virtual) và đào tạo trực tiếp tại lớp (offline)
